Workbook

Sheet COMPANY OVERVIEW
A43: …...............................................................................................................................................................................................................................................................................................................................................................................
A45: COMPANY BACKGOUND
A46: Hindustan Unilever Limited (HUL) is India’s largest FMCG company and has served Indian consumers for over 90 years, driven by a belief that ‘What is good for India, is good for HUL’. With a wide and resilient portfolio and a strong distribution network, we reach 9 out of 10 Indian households with at least one or more of our brands. Consumers Performance Overview Governance Overview Stakeholder Engagement and Review Statutory Reports Financial Statements Suppliers & Business Partners >85% Market leadership in categories we operate in We consistently cater to the evolving aspirations of Indian consumers through a strong focus on innovations. Keeping the needs of our consumers at the heart of our operations, we ensure that we deliver value to them through our unmissably superior brands while actively connecting with them via impactful, social-first marketing initiatives. We are strengthening our presence across channels of the future while leveraging our distinctive capabilities to create long-term value for all our stakeholders. As we embark on our journey of 'Unlocking a billion aspirations', we are supported by our two foundational pillars: Sustainability and Culture, while being guided by our core values of Integrity, Respect, Responsibility and Pioneering. Our best-in-class ESG ratings in the Indian FMCG sector and recognition as the #1 Employer of Choice across sectors underscores our commitment to responsible practices and our people, positioning us as a leader in the industry.
A59: Growth Drivers – Hindustan Unilever Limited | G59: Business Segments – Hindustan Unilever Limited
A61: Growth Driver | B61: Quantified Indicator (FY25) | C61: Explanation | D61: Valuation Significance | G61: Segment | H61: Revenue Contribution (Range %) | I61: Structural Positioning | J61: Business Description
A62: Market Leadership | B62: >85% categories led; 19 brands >₹1,000 Cr | C62: Strong brand equity and category dominance ensure revenue visibility. | D62: Supports long-term stable cash flows and pricing power. | G62: Home Care | H62: 36% – 39% | I62: Largest & Stable Contributor | J62: Fabric wash, household care, dishwash. Category leader in detergents & liquids. High volume base with gradual premiumisation.
A63: Distribution Scale | B63: 9 Mn+ outlets; 1.4 Mn retailers onboarded digitally | C63: Widest FMCG distribution reach in India; ~35% digitised demand capture. | D63: Creates structural entry barriers and operating leverage. | G63: Foods & Refreshments | H63: 24% – 26% | I63: Defensive & Cash Generative | J63: Tea leadership, growing coffee & health nutrition portfolio. Relatively stable demand profile.
A64: Volume Growth | B64: 2% Underlying Volume Growth | C64: Volume-led competitive growth despite demand moderation. | D64: Indicates resilient consumer demand base. | G64: Beauty & Wellbeing | H64: 20% – 23% | I64: Margin Accretive & Premiumisation Led | J64: Skincare, haircare, premium beauty brands. Higher gross margins vs portfolio average.
A65: Profitability Strength | B65: 23.5% EBITDA Margin; 17.5% PAT Margin | C65: Healthy margin profile maintained amid commodity volatility. | D65: Margin stability supports premium valuation multiples. | G65: Personal Care | H65: 14% – 16% | I65: Value Growth Segment | J65: Skin cleansing, oral care. Innovation & formulation upgrades drive competitiveness.
A66: Capital Efficiency | B66: 108.2% ROCE | C66: Efficient capital utilisation and high returns. | D66: Strong reinvestment capacity and shareholder value creation. | G66: Others | H66: 1% – 2% | I66: Emerging/Niche | J66: Smaller categories with selective expansion focus.
A67: Digital & AI Integration | B67: 35% forecasting improvement; 16% inventory reduction | C67: AI-enabled supply chain and production efficiency. | D67: Improves working capital cycle and cost optimisation. | G67: Contribution to the Indian Economy
A68: Sustainability Advantage | B68: 97% renewable energy usage; 99% Scope 1 & 2 emission reduction | C68: ESG-led operational model reduces regulatory and environmental risks. | D68: Enhances long-term risk-adjusted valuation. | G68: Area | H68: Long-Term Contribution
A69: Dividend Strength | B69: ₹53 per share; ₹12,453 Cr payout | C69: Strong cash generation enables consistent shareholder returns. | D69: Improves investor confidence and total shareholder return. | G69: Revenue Scale | H69: ₹60,000+ Cr annual turnover level
G70: Employment | H70: 18,000+ direct employees + extensive indirect employment
G71: Distribution Network | H71: 9M+ retail outlets; 3,500+ distributors
G72: Manufacturing Base | H72: 25+ factories across India
G73: Farmer & SME Linkage | H73: Lakhs of farmers & MSMEs integrated in value chain
G74: Tax & Dividend Contribution | H74: ₹10,000+ Cr PAT annually; consistent dividend payout
G75: Household Penetration | H75: 9 out of 10 Indian households

Sheet Economic Analysis Enhanced
A1: INDIA MACROECONOMIC ANALYSIS — FMCG DEMAND CORRELATION (2015–2025)
A2: Variables: GDP Growth | CPI Inflation | Repo Rate | USD/INR | Disposable Income | FMCG Sector Growth
A3: SECTION A — MACROECONOMIC DATASET (2015–2025)
B4: Year | C4: GDP Growth % | D4: CPI Inflation % | E4: Repo Rate % | F4: USD/INR Rate | G4: Disp. Income (₹ Tr) | H4: FMCG Sector Growth % | I4: FMCG Mkt Size ($B)
B5: 2015 | C5: 0.0797 | D5: 0.0491 | E5: 0.0775 | F5: 64.15 | G5: 72.4 | H5: 0.065 | I5: 95
B6: 2016 | C6: 0.0826 | D6: 0.0495 | E6: 0.065 | F6: 66.46 | G6: 75.8 | H6: 0.07 | I6: 102
B7: 2017 | C7: 0.068 | D7: 0.0333 | E7: 0.0625 | F7: 67.79 | G7: 79.2 | H7: 0.058 | I7: 110
B8: 2018 | C8: 0.0645 | D8: 0.0394 | E8: 0.065 | F8: 70.09 | G8: 83.5 | H8: 0.092 | I8: 120
B9: 2019 | C9: 0.0387 | D9: 0.0373 | E9: 0.0515 | F9: 70.39 | G9: 87.4 | H9: 0.064 | I9: 128
B10: 2020 | C10: -0.0578 | D10: 0.0618 | E10: 0.04 | F10: 76.38 | G10: 82 | H10: -0.021 | I10: 125
B11: 2021 | C11: 0.0969 | D11: 0.0513 | E11: 0.04 | F11: 74.57 | G11: 88.6 | H11: 0.148 | I11: 144
B12: 2022 | C12: 0.0699 | D12: 0.067 | E12: 0.0625 | F12: 81.35 | G12: 95.2 | H12: 0.082 | I12: 156
B13: 2023 | C13: 0.0815 | D13: 0.0565 | E13: 0.065 | F13: 81.94 | G13: 103.8 | H13: 0.105 | I13: 172
B14: 2024 | C14: 0.082 | D14: 0.0485 | E14: 0.065 | F14: 83.7 | G14: 112.4 | H14: 0.08 | I14: 186
B15: 2025 | C15: 0.064 | D15: 0.042 | E15: 0.0625 | F15: 84.1 | G15: 119.6 | H15: 0.065 | I15: 198
A17: SECTION B — YEAR-ON-YEAR DELTA TABLE
B18: Year | C18: ΔGDP (pp) | D18: ΔCPI (pp) | E18: ΔRepo (pp) | F18: ΔUSD/INR | G18: ΔDisp. Inc (₹ Tr) | H18: ΔFMCG Growth (pp) | I18: ΔMkt Size ($B)
B19: 2016 | C19: 0.0029 | D19: 0.0004 | E19: -0.0125 | F19: 2.31 | G19: 3.4 | H19: 0.005 | I19: 7
B20: 2017 | C20: -0.0146 | D20: -0.0162 | E20: -0.0025 | F20: 1.33 | G20: 3.4 | H20: -0.012 | I20: 8
B21: 2018 | C21: -0.0035 | D21: 0.0061 | E21: 0.0025 | F21: 2.3 | G21: 4.3 | H21: 0.034 | I21: 10
B22: 2019 | C22: -0.0258 | D22: -0.0021 | E22: -0.0135 | F22: 0.3 | G22: 3.9 | H22: -0.028 | I22: 8
B23: 2020 | C23: -0.0965 | D23: 0.0245 | E23: -0.0115 | F23: 5.99 | G23: -5.4 | H23: -0.085 | I23: -3
B24: 2021 | C24: 0.1547 | D24: -0.0105 | E24: 0 | F24: -1.81 | G24: 6.6 | H24: 0.169 | I24: 19
B25: 2022 | C25: -0.027 | D25: 0.0157 | E25: 0.0225 | F25: 6.78 | G25: 6.6 | H25: -0.066 | I25: 12
B26: 2023 | C26: 0.0116 | D26: -0.0105 | E26: 0.0025 | F26: 0.59 | G26: 8.6 | H26: 0.023 | I26: 16
B27: 2024 | C27: 0.0005 | D27: -0.008 | E27: 0 | F27: 1.76 | G27: 8.6 | H27: -0.025 | I27: 14
B28: 2025 | C28: -0.018 | D28: -0.0065 | E28: -0.0025 | F28: 0.4 | G28: 7.2 | H28: -0.015 | I28: 12
A30: SECTION C — CORRELATION WITH FMCG DEMAND
B31: Macro Variable | C31: Pearson Corr. | D31: Directional Impact | E31: Insight for HUL
B32: GDP Growth Rate | C32: +0.78 | D32: Positive | E32: Strong — rising incomes boost FMCG volumes; HUL top-line closely tracks GDP cycles.
B33: CPI Inflation (Food & Bev) | C33: -0.52 | D33: Negative | E33: High food inflation compresses real wages → volume decline especially in mass segments.
B34: RBI Repo Rate | C34: -0.41 | D34: Negative | E34: Higher rates tighten rural credit; dampens FMCG trade pipeline financing.
B35: USD/INR Depreciation | C35: -0.35 | D35: Negative | E35: Raises cost of palm oil, crude derivatives — HUL raw material basket ~55% commodity-linked.
B36: Disposable Income Proxy | C36: +0.85 | D36: Positive | E36: Strongest predictor; rural income growth is single most important driver for HUL volumes.
B37: E-commerce Channel Growth | C37: +0.71 | D37: Positive | E37: Emerging high-correlation factor; HUL D2C + quick commerce accelerating share gains.
A39: SECTION D — KEY MACROECONOMIC INTERPRETATION FOR HUL (5–6 BULLET INSIGHTS)
B40: • GDP Bounce-back Effect: India's post-COVID recovery (FY21: +9.7%) directly catalysed FMCG volume recovery; HUL revenue grew 18.4% in FY2021, confirming strong GDP-demand linkage.
B41: • Inflation Double-Edged Impact: Rising CPI (FY20: 6.2%, FY22: 6.7%) pressured HUL gross margins via higher palm oil & LAB costs; partially offset by strategic 5–8% pricing actions across categories.
B42: • Disposable Income is the Lead Indicator: The disposable income proxy (₹72Tr→₹120Tr over 2015–25) shows +0.85 correlation with FMCG growth — rural wage growth (MGNREGA, MSP hikes) is the key swing variable for HUL's rural 40% revenue contribution.
B43: • Currency Risk is Manageable: INR depreciation (₹64→₹84 over decade) raised input costs but HUL's global procurement via Unilever's scale, combined with selective price hikes, maintains gross margin in 25–32% band.
B44: • Rate Normalization Poses Limited Risk: RBI's repo rate hike from 4% to 6.5% (2021–23) increased trade financing costs; however, HUL's interest coverage of 40x+ renders this immaterial to financial health.
B45: • E-commerce Structural Tailwind: FMCG e-commerce share grew from ~2% (2015) to ~12%+ (2025); HUL's investments in Mera Seva ecosystem, quick commerce partnerships, and premium D2C brands positions it well for the next decade of consumption growth.
A46: Source: RBI Monetary Policy Reports, MoSPI National Accounts, World Bank WDI, IBEF FMCG Reports, DPIIT, HUL Annual Reports. Correlation coefficients are approximate.

Sheet Industrial analysis
BK9: Year | BL9: FMCG Market Size ($ Billion) | BM9: Urban Demand Share % | BN9: Rural Demand Share % | BO9: FMCG Industry Growth % | BP9: E-commerce FMCG Share % | BQ9: Organized Sector Share %
BK10: 2015 | BL10: 95 | BM10: 63 | BN10: 37 | BO10: 6.5 | BP10: 2 | BQ10: 58
BK11: 2016 | BL11: 102 | BM11: 63 | BN11: 37 | BO11: 7 | BP11: 2.5 | BQ11: 59
BK12: 2017 | BL12: 110 | BM12: 62 | BN12: 38 | BO12: 7.5 | BP12: 3 | BQ12: 60
BK13: 2018 | BL13: 120 | BM13: 62 | BN13: 38 | BO13: 8 | BP13: 4 | BQ13: 62
BK14: 2019 | BL14: 130 | BM14: 62 | BN14: 38 | BO14: 7 | BP14: 5 | BQ14: 64
BK15: 2020 | BL15: 125 | BM15: 61 | BN15: 39 | BO15: 3 | BP15: 7 | BQ15: 66
BK16: 2021 | BL16: 150 | BM16: 61 | BN16: 39 | BO16: 8 | BP16: 9 | BQ16: 68
BK17: 2022 | BL17: 180 | BM17: 62 | BN17: 38 | BO17: 9 | BP17: 11 | BQ17: 70
BK18: 2023 | BL18: 210 | BM18: 62 | BN18: 38 | BO18: 8 | BP18: 13 | BQ18: 72
BK19: 2024 | BL19: 245 | BM19: 62 | BN19: 38 | BO19: 6 | BP19: 15 | BQ19: 74
BK20: 2025 | BL20: 288 | BM20: 61 | BN20: 39 | BO20: 7 | BP20: 18 | BQ20: 76

Sheet table of content
A2: Table of content
B4: Sr No. | C4: Particulars | D4: Content
B5: 1 | C5: Sources | D5: Base of Assumptions taken for DCF Valuation
B6: 2 | C6: Assumptions | D6: Assumption taken for DCF Valuation
B7: 3 | C7: Financial Statements | D7: Forecasted financial statements
B8: 4 | C8: PPE Schedule | D8: Supporting Schedule for calculating the cash flows
B9: 5 | C9: Beta | D9: Calculation of Beta
B10: 6 | C10: WACC | D10: Calculation of WACC
B11: 7 | C11: DCF Valuation | D11: DCF Valuation of Tata Steel Ltd.
B12: 8 | C12: Relative Valuation | D12: Relative valuation with companies (JSW Steel, Hindalco, and Jindal Steel)
B13: 9 | C13: All Ratio Forecast | D13: Calculation of ratios for Tata Steel
B14: 10 | C14: Key Ratio Forecast | D14: Calculation of key ratios for Tata Steel

Sheet SOURCES
A1: Bases and Sources of the data/assumption used in the valuation.
A3: Sl. No. | B3: Detail of Assumption/Data point | C3: Assumed Figure | D3: Remarks | E3: URL
A4: 1 | B4: Actual Financial Statement data for last 5 years | C4: 0 | D4: Financial statements has been taken for the last five years from capitaline database | E4: https://awsone.capitaline.com/index.html#/Company/Condensed/condensed?
B5: Revenue Growth | C5: 0.0961 | D5: India's steel consumption is predicted to increase by 230 MT by 2030 from 130 MT in 2022 as per ibef report. Therefore, an average of 9.61% gowth every year. | E5: https://www.ibef.org/industry/steel/showcase/tata-steel
A6: 2 | B6: Tax Rate | C6: 0.25168 | D6: As mentioned in Annual Report 2022 | E6: https://www.tatasteel.com/media/15928/tata-steel-ir-2021-22.pdf
A7: 3 | B7: Data period used for Stock and Market Index Price | C7: 0 | D7: 5 years daily price changes of BSE Sensex and Tata Steel Ltd. has been used to calculate Beta. | E7: https://www.bseindia.com/markets/equity/EQReports/StockPrcHistori
A8: 4 | B8: Risk Free Rate | C8: 0.0737 | D8: Risk free rate is 10 year government yield bond rate as on 07-01-2023 | E8: http://www.worldgovernmentbonds.com/bond-historical-data/india/10-years/
A9: 5 | B9: Market Risk Premium | C9: 0.0685 | D9: Equity Risk premium of India is 6.85% as per knoema | E9: https://knoema.com/NYCCDSRP2019JAN/country-default-spreads-and-risk-premiums?tsId=1004460
A10: 6 | B10: Perpetuity Growth Rate for Terminal Value | C10: 0.0702 | D10: Ideally, it should not exceed the growth rate of economy. And one of the proxy for economy growth rate could be GDP growth. Hence, an approximate 7.02% growth rate has been taken based on the average GDP growth rate of 5 years starting 2016 to 2021. GDP growth for 2020-2021 @ -7.97% has been excluded from the average. | E10: https://data.worldbank.org/indicator/NY.GDP.MKTP.KD.ZG?locations=IN
A11: 7 | B11: Basis for selection of peer companies | C11: 0 | D11: Top 4 steel producers (Market Capitalization) in India | E11: https://www.moneycontrol.com/stocks/marketinfo/marketcap/bse/iron-steel.html
A12: 8 | B12: Sensitivity Analysis | C12: 0 | D12: In this valuation, two variable sensitivity analysis has been used based on WACC and perpetual growth rate
A13: 9 | B13: Peer Comparison | C13: 0 | D13: For peer comparison, the data and ratios has been taken from money control and smart investing | E13: https://www.moneycontrol.com/india/stockpricequote/steel-large/

Sheet HUL ASSUMPTION 
A3: BALANCE SHEET
A5: Balance sheet | B5: Balance sheet2 | C5: Balance sheet3 | D5: Balance sheet4 | E5: balance sheet5 | F5: Balance sheet6 | G5: Balance sheet11 | H5: Balance sheet7 | I5: Balance sheet8 | J5: Balance sheet9 | K5: Balance sheet10 | L5: Balance sheet102 | M5: Balance sheet103 | N5: Balance sheet104 | O5: Balance sheet105 | P5: Balance sheet106 | Q5: Balance sheet107
A6: Year | B6: 2016 | C6: 2017 | D6: 2018 | E6: 2019 | F6: 2020 | G6: 2021 | H6: 2022 | I6: 2023 | J6: 2024 | K6: 2025 | L6: 2026 | M6: 2027 | N6: 2028 | O6: 2029 | P6: 2030 | Q6: GROWTH
A7: SOURCES OF FUNDS :
A8: Share Capital | B8: 216 | C8: 216 | D8: 216 | E8: 216 | F8: 216 | G8: 235 | H8: 235 | I8: 235 | J8: 235 | K8: 235 | L8: 235 | M8: 235 | N8: 235 | O8: 235 | P8: 235
A9: Reserves Total | B9: 6063 | C9: 6274 | D9: 6859 | E9: 7443 | F9: 7815 | G9: 47199 | H9: 48525 | I9: 49986 | J9: 50738 | K9: 48918 | L9: =Table4[[#This Row],[Balance sheet10]]*(1+$Q$12) -> 48918 | M9: =Table4[[#This Row],[Balance sheet102]]*(1+$Q$12) -> 48918 | N9: =Table4[[#This Row],[Balance sheet103]]*(1+$Q$12) -> 48918 | O9: =Table4[[#This Row],[Balance sheet104]]*(1+$Q$12) -> 48918 | P9: =Table4[[#This Row],[Balance sheet105]]*(1+$Q$12) -> 48918
A10: Total Shareholders Funds | B10: 6279 | C10: 6490 | D10: 7075 | E10: 7659 | F10: 8031 | G10: 47434 | H10: 48760 | I10: 50221 | J10: 50973 | K10: 49153 | L10: =L9+L8 -> 49153 | M10: =M9+M8 -> 49153 | N10: =N9+N8 -> 49153 | O10: =O9+O8 -> 49153 | P10: =P9+P8 -> 49153
A11: Unsecured Loans | B11: 0 | C11: 0 | D11: 0 | E11: 0 | F11: 0 | G11: 943 | H11: 971 | I11: 1039 | J11: 1374 | K11: 1537 | L11: =Table4[[#This Row],[Balance sheet10]]*(1+$Q$13) -> 1629.3533 | M11: =Table4[[#This Row],[Balance sheet102]]*(1+$Q$13) -> 1727.2558 | N11: =Table4[[#This Row],[Balance sheet103]]*(1+$Q$13) -> 1831.0409 | O11: =Table4[[#This Row],[Balance sheet104]]*(1+$Q$13) -> 1941.0622 | P11: =Table4[[#This Row],[Balance sheet105]]*(1+$Q$13) -> 2057.6942
A12: Total Debt | B12: 0 | C12: 0 | D12: 0 | E12: 0 | F12: 0 | G12: 943 | H12: 971 | I12: 1039 | J12: 1374 | K12: 1537 | L12: =Table4[[#This Row],[Balance sheet10]]*(1+$Q$13) -> 1629.3533 | M12: =Table4[[#This Row],[Balance sheet102]]*(1+$Q$13) -> 1727.2558 | N12: =Table4[[#This Row],[Balance sheet103]]*(1+$Q$13) -> 1831.0409 | O12: =Table4[[#This Row],[Balance sheet104]]*(1+$Q$13) -> 1941.0622 | P12: =Table4[[#This Row],[Balance sheet105]]*(1+$Q$13) -> 2057.6942
A13: YOY | C13: 0 | D13: 0 | E13: 0 | F13: 0 | G13: 0 | H13: =(H12-G12)/G12 -> 0.029692471 | I13: =(I12-H12)/H12 -> 0.070030896 | J13: =(J12-I12)/I12 -> 0.32242541 | K13: =(K12-J12)/J12 -> 0.11863173 | Q13: =AVERAGE(Table4[[#This Row],[Balance sheet2]:[Balance sheet10]]) -> 0.060086723
A14: Other Liabilities | B14: 989 | C14: 1059 | D14: 1438 | E14: 1853 | F14: 2467 | G14: 3176 | H14: 3206 | I14: 2906 | J14: 6212 | K14: 5748
A15: Total Liabilities | B15: 7268 | C15: 7549 | D15: 8513 | E15: 9512 | F15: 10498 | G15: 51553 | H15: 52937 | I15: 54166 | J15: 58559 | K15: 56438
A16: APPLICATION OF FUNDS :
A17: Gross Block | B17: 3218 | C17: 4712 | D17: 5267 | E17: 5959 | F17: 7375 | G17: 54192 | H17: 54799 | I17: 55864 | J17: 57603 | K17: 58790 | L17: =Table4[[#This Row],[Balance sheet10]]*(1+$Q$18) -> 60000.652 | M17: =Table4[[#This Row],[Balance sheet102]]*(1+$Q$18) -> 61236.236 | N17: =Table4[[#This Row],[Balance sheet103]]*(1+$Q$18) -> 62497.263 | O17: =Table4[[#This Row],[Balance sheet104]]*(1+$Q$18) -> 63784.258 | P17: =Table4[[#This Row],[Balance sheet105]]*(1+$Q$18) -> 65097.756
A18: YOY | C18: =(C17-B17)/B17 -> 0.46426352 | D18: =(D17-C17)/C17 -> 0.11778438 | E18: =(E17-D17)/D17 -> 0.13138409 | F18: =(F17-E17)/E17 -> 0.23762376 | G18: =(G17-F17)/F17 -> 6.3480678 | H18: =(H17-G17)/G17 -> 0.011200915 | I18: =(I17-H17)/H17 -> 0.019434661 | J18: =(J17-I17)/I17 -> 0.031129171 | K18: =(K17-J17)/J17 -> 0.020606566 | Q18: =AVERAGE(Table4[[#This Row],[Balance sheet7]:[Balance sheet10]]) -> 0.020592828
A19: Less : Accumulated Depreciation | B19: 304 | C19: 688 | D19: 1125 | E19: 1616 | F19: 2319 | G19: 3165 | H19: 3765 | I19: 4459 | J19: 5224 | K19: 5883
A20: Net Block | B20: 2914 | C20: 4024 | D20: 4142 | E20: 4343 | F20: 5056 | G20: 51027 | H20: 51034 | I20: 51405 | J20: 52379 | K20: 52907
A21: YOY | C21: =(C20-B20)/B20 -> 0.3809197 | D21: =(D20-C20)/C20 -> 0.029324056 | E21: =(E20-D20)/D20 -> 0.048527282 | F21: =(F20-E20)/E20 -> 0.16417223 | G21: =(G20-F20)/F20 -> 9.0923655 | H21: =(H20-G20)/G20 -> 0.00013718228 | I21: =(I20-H20)/H20 -> 0.0072696634 | J21: =(J20-I20)/I20 -> 0.018947573 | K21: =(K20-J20)/J20 -> 0.010080376 | Q21: =AVERAGE(C21:F21,H21:K21) -> 0.082422258
A22: Capital Work in Progress | B22: 386 | C22: 203 | D22: 430 | E22: 373 | F22: 513 | G22: 623 | H22: 901 | I22: 1020 | J22: 915 | K22: 956 | L22: =Table4[[#This Row],[Balance sheet10]]*(1+$Q$26) -> 988.4402 | M22: =Table4[[#This Row],[Balance sheet102]]*(1+$Q$26) -> 1021.9812 | N22: =Table4[[#This Row],[Balance sheet103]]*(1+$Q$26) -> 1056.6604 | O22: =Table4[[#This Row],[Balance sheet104]]*(1+$Q$26) -> 1092.5163 | P22: =Table4[[#This Row],[Balance sheet105]]*(1+$Q$26) -> 1129.5889
A23: Investments | B23: 2780 | C23: 3779 | D23: 3111 | E23: 2949 | F23: 1500 | G23: 2995 | H23: 4122 | I23: 3794 | J23: 5493 | K23: 4602 | L23: =Table4[[#This Row],[Balance sheet10]]*(1+$Q$26) -> 4758.1609 | M23: =Table4[[#This Row],[Balance sheet102]]*(1+$Q$26) -> 4919.6208 | N23: =Table4[[#This Row],[Balance sheet103]]*(1+$Q$26) -> 5086.5596 | O23: =Table4[[#This Row],[Balance sheet104]]*(1+$Q$26) -> 5259.1631 | P23: =Table4[[#This Row],[Balance sheet105]]*(1+$Q$26) -> 5437.6237
A24: Current Assets, Loans & Advances | L24: =Table4[[#This Row],[Balance sheet10]]*(1+$Q$26) -> 0 | M24: =Table4[[#This Row],[Balance sheet102]]*(1+$Q$26) -> 0 | N24: =Table4[[#This Row],[Balance sheet103]]*(1+$Q$26) -> 0 | O24: =Table4[[#This Row],[Balance sheet104]]*(1+$Q$26) -> 0 | P24: =Table4[[#This Row],[Balance sheet105]]*(1+$Q$26) -> 0
A25: Inventories | B25: 2528 | C25: 2362 | D25: 2359 | E25: 2422 | F25: 2636 | G25: 3383 | H25: 3890 | I25: 4031 | J25: 3812 | K25: 4161 | L25: =Table4[[#This Row],[Balance sheet10]]*(1+$Q$26) -> 4302.1963 | M25: =Table4[[#This Row],[Balance sheet102]]*(1+$Q$26) -> 4448.1839 | N25: =Table4[[#This Row],[Balance sheet103]]*(1+$Q$26) -> 4599.1253 | O25: =Table4[[#This Row],[Balance sheet104]]*(1+$Q$26) -> 4755.1886 | P25: =Table4[[#This Row],[Balance sheet105]]*(1+$Q$26) -> 4916.5476
A26: YOY | C26: =(C25-B25)/B25 -> -0.065664557 | D26: =(D25-C25)/C25 -> -0.0012701101 | E26: =(E25-D25)/D25 -> 0.026706231 | F26: =(F25-E25)/E25 -> 0.08835673 | G26: =(G25-F25)/F25 -> 0.28338392 | H26: =(H25-G25)/G25 -> 0.14986698 | I26: =(I25-H25)/H25 -> 0.036246787 | J26: =(J25-I25)/I25 -> -0.054328951 | K26: =(K25-J25)/J25 -> 0.091552991 | Q26: =AVERAGE(C26:F26,H26:K26) -> 0.033933263
A27: Sundry Debtors | B27: 1064 | C27: 928 | D27: 1147 | E27: 1673 | F27: 1046 | G27: 1648 | H27: 1932 | I27: 2735 | J27: 2690 | K27: 3450 | L27: =Table4[[#This Row],[Balance sheet10]]*(1+$Q$31) -> 3847.796 | M27: =Table4[[#This Row],[Balance sheet102]]*(1+$Q$31) -> 4291.4591 | N27: =Table4[[#This Row],[Balance sheet103]]*(1+$Q$31) -> 4786.278 | O27: =Table4[[#This Row],[Balance sheet104]]*(1+$Q$31) -> 5338.1512 | P27: =Table4[[#This Row],[Balance sheet105]]*(1+$Q$31) -> 5953.657
A28: Cash and Bank | B28: 2759 | C28: 1671 | D28: 3373 | E28: 3688 | F28: 5017 | G28: 4321 | H28: 3618 | I28: 4422 | J28: 7216 | K28: 7293 | L28: =Table4[[#This Row],[Balance sheet10]]*(1+$Q$31) -> 8133.9061 | M28: =Table4[[#This Row],[Balance sheet102]]*(1+$Q$31) -> 9071.7714 | N28: =Table4[[#This Row],[Balance sheet103]]*(1+$Q$31) -> 10117.776 | O28: =Table4[[#This Row],[Balance sheet104]]*(1+$Q$31) -> 11284.387 | P28: =Table4[[#This Row],[Balance sheet105]]*(1+$Q$31) -> 12585.513
A29: Loans and Advances | B29: 740 | C29: 885 | D29: 1405 | E29: 898 | F29: 1961 | G29: 1605 | H29: 1697 | I29: 2050 | J29: 2068 | K29: 2381 | L29: =Table4[[#This Row],[Balance sheet10]]*(1+$Q$31) -> 2655.5369 | M29: =Table4[[#This Row],[Balance sheet102]]*(1+$Q$31) -> 2961.7288 | N29: =Table4[[#This Row],[Balance sheet103]]*(1+$Q$31) -> 3303.2255 | O29: =Table4[[#This Row],[Balance sheet104]]*(1+$Q$31) -> 3684.0979 | P29: =Table4[[#This Row],[Balance sheet105]]*(1+$Q$31) -> 4108.8862
A30: Total Current Assets | B30: 7091 | C30: 5846 | D30: 8284 | E30: 8681 | F30: 10660 | G30: 10957 | H30: 11137 | I30: 13238 | J30: 15786 | K30: 17285 | L30: =Table4[[#This Row],[Balance sheet10]]*(1+$Q$31) -> 19278.016 | M30: =Table4[[#This Row],[Balance sheet102]]*(1+$Q$31) -> 21500.832 | N30: =Table4[[#This Row],[Balance sheet103]]*(1+$Q$31) -> 23979.947 | O30: =Table4[[#This Row],[Balance sheet104]]*(1+$Q$31) -> 26744.911 | P30: =Table4[[#This Row],[Balance sheet105]]*(1+$Q$31) -> 29828.684
A31: YOY | C31: =(C30-B30)/B30 -> -0.17557467 | D31: =(D30-C30)/C30 -> 0.41703729 | E31: =(E30-D30)/D30 -> 0.047923708 | F31: =(F30-E30)/E30 -> 0.22796913 | G31: =(G30-F30)/F30 -> 0.027861163 | H31: =(H30-G30)/G30 -> 0.016427854 | I31: =(I30-H30)/H30 -> 0.18865044 | J31: =(J30-I30)/I30 -> 0.1924762 | K31: =(K30-J30)/J30 -> 0.094957557 | Q31: =AVERAGE(Table4[[#This Row],[Balance sheet2]:[Balance sheet10]]) -> 0.11530319
A32: Less : Current Liabilities and Provisions
A33: Current Liabilities | B33: 6362 | C33: 6815 | D33: 7985 | E33: 7852 | F33: 8686 | G33: 10086 | H33: 10325 | I33: 10955 | J33: 11734 | K33: 12744 | L33: =Table4[[#This Row],[Balance sheet10]]*(1+$Q$36) -> 14023.789 | M33: =Table4[[#This Row],[Balance sheet102]]*(1+$Q$36) -> 15432.097 | N33: =Table4[[#This Row],[Balance sheet103]]*(1+$Q$36) -> 16981.832 | O33: =Table4[[#This Row],[Balance sheet104]]*(1+$Q$36) -> 18687.196 | P33: =Table4[[#This Row],[Balance sheet105]]*(1+$Q$36) -> 20563.817
A34: Provisions | B34: 290 | C34: 387 | D34: 651 | E34: 501 | F34: 418 | G34: 491 | H34: 334 | I34: 379 | J34: 329 | K34: 2548 | L34: =Table4[[#This Row],[Balance sheet10]]*(1+$Q$36) -> 2803.8774 | M34: =Table4[[#This Row],[Balance sheet102]]*(1+$Q$36) -> 3085.4507 | N34: =Table4[[#This Row],[Balance sheet103]]*(1+$Q$36) -> 3395.3004 | O34: =Table4[[#This Row],[Balance sheet104]]*(1+$Q$36) -> 3736.2661 | P34: =Table4[[#This Row],[Balance sheet105]]*(1+$Q$36) -> 4111.4725
A35: Total Current Liabilities | B35: 6652 | C35: 7202 | D35: 8636 | E35: 8353 | F35: 9104 | G35: 10577 | H35: 10659 | I35: 11334 | J35: 12063 | K35: 15292 | L35: =Table4[[#This Row],[Balance sheet10]]*(1+$Q$36) -> 16827.666 | M35: =Table4[[#This Row],[Balance sheet102]]*(1+$Q$36) -> 18517.548 | N35: =Table4[[#This Row],[Balance sheet103]]*(1+$Q$36) -> 20377.132 | O35: =Table4[[#This Row],[Balance sheet104]]*(1+$Q$36) -> 22423.462 | P35: =Table4[[#This Row],[Balance sheet105]]*(1+$Q$36) -> 24675.289
A36: YOY | C36: =(C35-B35)/B35 -> 0.0826819 | D36: =(D35-C35)/C35 -> 0.19911136 | E36: =(E35-D35)/D35 -> -0.032769801 | F36: =(F35-E35)/E35 -> 0.089907818 | G36: =(G35-F35)/F35 -> 0.16179701 | H36: =(H35-G35)/G35 -> 0.0077526709 | I36: =(I35-H35)/H35 -> 0.063326766 | J36: =(J35-I35)/I35 -> 0.064319746 | K36: =(K35-J35)/J35 -> 0.26767802 | Q36: =AVERAGE(Table4[[#This Row],[Balance sheet2]:[Balance sheet10]]) -> 0.10042283
A37: Net Current Assets | B37: 439 | C37: -1356 | D37: -352 | E37: 328 | F37: 1556 | G37: 380 | H37: 478 | I37: 1904 | J37: 3723 | K37: 1993 | L37: =Table4[[#This Row],[Balance sheet10]]*(1+$Q$43) -> 2113.1568 | M37: =Table4[[#This Row],[Balance sheet102]]*(1+$Q$43) -> 2240.5577 | N37: =Table4[[#This Row],[Balance sheet103]]*(1+$Q$43) -> 2375.6396 | O37: =Table4[[#This Row],[Balance sheet104]]*(1+$Q$43) -> 2518.8655 | P37: =Table4[[#This Row],[Balance sheet105]]*(1+$Q$43) -> 2670.7264
A38: Deferred Tax Assets | B38: 510 | C38: 572 | D38: 653 | E38: 778 | F38: 534 | G38: 655 | H38: 477 | I38: 471 | J38: 583 | K38: 491 | L38: =Table4[[#This Row],[Balance sheet10]]*(1+$Q$43) -> 520.6021 | M38: =Table4[[#This Row],[Balance sheet102]]*(1+$Q$43) -> 551.98889 | N38: =Table4[[#This Row],[Balance sheet103]]*(1+$Q$43) -> 585.26797 | O38: =Table4[[#This Row],[Balance sheet104]]*(1+$Q$43) -> 620.55342 | P38: =Table4[[#This Row],[Balance sheet105]]*(1+$Q$43) -> 657.96622
A39: Deferred Tax Liability | B39: 342 | C39: 412 | D39: 398 | E39: 439 | F39: 273 | G39: 6641 | H39: 6618 | I39: 6796 | J39: 7037 | K39: 7074 | L39: =Table4[[#This Row],[Balance sheet10]]*(1+$Q$43) -> 7500.4872 | M39: =Table4[[#This Row],[Balance sheet102]]*(1+$Q$43) -> 7952.6871 | N39: =Table4[[#This Row],[Balance sheet103]]*(1+$Q$43) -> 8432.1499 | O39: =Table4[[#This Row],[Balance sheet104]]*(1+$Q$43) -> 8940.5192 | P39: =Table4[[#This Row],[Balance sheet105]]*(1+$Q$43) -> 9479.5378
A40: Net Deferred Tax | B40: 168 | C40: 160 | D40: 255 | E40: 339 | F40: 261 | G40: -5986 | H40: -6141 | I40: -6325 | J40: -6454 | K40: -6583 | L40: =Table4[[#This Row],[Balance sheet10]]*(1+$Q$43) -> -6979.8851 | M40: =Table4[[#This Row],[Balance sheet102]]*(1+$Q$43) -> -7400.6983 | N40: =Table4[[#This Row],[Balance sheet103]]*(1+$Q$43) -> -7846.8819 | O40: =Table4[[#This Row],[Balance sheet104]]*(1+$Q$43) -> -8319.9658 | P40: =Table4[[#This Row],[Balance sheet105]]*(1+$Q$43) -> -8821.5715
A41: Other Assets | B41: 581 | C41: 739 | D41: 927 | E41: 1180 | F41: 1612 | G41: 2514 | H41: 2543 | I41: 2368 | J41: 2503 | K41: 2563 | L41: =Table4[[#This Row],[Balance sheet10]]*(1+$Q$43) -> 2717.5217 | M41: =Table4[[#This Row],[Balance sheet102]]*(1+$Q$43) -> 2881.3595 | N41: =Table4[[#This Row],[Balance sheet103]]*(1+$Q$43) -> 3055.0749 | O41: =Table4[[#This Row],[Balance sheet104]]*(1+$Q$43) -> 3239.2636 | P41: =Table4[[#This Row],[Balance sheet105]]*(1+$Q$43) -> 3434.5569
A42: Total Assets | B42: 7268 | C42: 7549 | D42: 8513 | E42: 9512 | F42: 10498 | G42: 51553 | H42: 52937 | I42: 54166 | J42: 58559 | K42: 56438 | L42: =Table4[[#This Row],[Balance sheet10]]*(1+$Q$43) -> 59840.613 | M42: =Table4[[#This Row],[Balance sheet102]]*(1+$Q$43) -> 63448.368 | N42: =Table4[[#This Row],[Balance sheet103]]*(1+$Q$43) -> 67273.632 | O42: =Table4[[#This Row],[Balance sheet104]]*(1+$Q$43) -> 71329.52 | P42: =Table4[[#This Row],[Balance sheet105]]*(1+$Q$43) -> 75629.934
A43: YOY | C43: =(C42-B42)/B42 -> 0.038662631 | D43: =(D42-C42)/C42 -> 0.12769903 | E43: =(E42-D42)/D42 -> 0.11734994 | F43: =(F42-E42)/E42 -> 0.10365854 | G43: =(G42-F42)/F42 -> 3.9107449 | H43: =(H42-G42)/G42 -> 0.026846158 | I43: =(I42-H42)/H42 -> 0.023216276 | J43: =(J42-I42)/I42 -> 0.081102537 | K43: =(K42-J42)/J42 -> -0.036219881 | Q43: =AVERAGE(C43:F43,H43:K43) -> 0.060289403
A44: Contingent Liabilities | B44: 1026 | C44: 987 | D44: 1539 | E44: 1726 | F44: 2260 | G44: 2086 | H44: 2321 | I44: 2577 | J44: 2422 | K44: 2446
A45: Average inventory | C45: =(C25+B25)/2 -> 2445 | D45: =(D25+C25)/2 -> 2360.5 | E45: =(E25+D25)/2 -> 2390.5 | F45: =(F25+E25)/2 -> 2529 | G45: =(G25+F25)/2 -> 3009.5 | H45: =(H25+G25)/2 -> 3636.5 | I45: =(I25+H25)/2 -> 3960.5 | J45: =(J25+I25)/2 -> 3921.5 | K45: =(K25+J25)/2 -> 3986.5
A46: Average Trade Receivables | C46: =(C27+B27)/2 -> 996 | D46: =(D27+C27)/2 -> 1037.5 | E46: =(E27+D27)/2 -> 1410 | F46: =(F27+E27)/2 -> 1359.5 | G46: =(G27+F27)/2 -> 1347 | H46: =(H27+G27)/2 -> 1790 | I46: =(I27+H27)/2 -> 2333.5 | J46: =(J27+I27)/2 -> 2712.5 | K46: =(K27+J27)/2 -> 3070
A47: Average Trade Payables | C47: =(C33+B33)/2 -> 6588.5 | D47: =(D33+C33)/2 -> 7400 | E47: =(E33+D33)/2 -> 7918.5 | F47: =(F33+E33)/2 -> 8269 | G47: =(G33+F33)/2 -> 9386 | H47: =(H33+G33)/2 -> 10205.5 | I47: =(I33+H33)/2 -> 10640 | J47: =(J33+I33)/2 -> 11344.5 | K47: =(K33+J33)/2 -> 12239
A48: WORKING CAPITA | B48: =B30-B33 -> 729 | C48: =C30-C33 -> -969 | D48: =D30-D33 -> 299 | E48: =E30-E33 -> 829 | F48: =F30-F33 -> 1974 | G48: =G30-G33 -> 871 | H48: =H30-H33 -> 812 | I48: =I30-I33 -> 2283 | ... P48: =P30-P33 -> 9264.8675
A49: CHANGE IN WORKING CAPITAL | C49: =C48-B48 -> -1698 | D49: =D48-C48 -> 1268 | E49: =E48-D48 -> 530 | F49: =F48-E48 -> 1145 | G49: =G48-F48 -> -1103 | H49: =H48-G48 -> -59 | I49: =I48-H48 -> 1471 | J49: =J48-I48 -> 1769 | ... P49: =P48-O48 -> 1207.1523
A50: Capex | C50: =C17-B17 -> 1494 | D50: =D17-C17 -> 555 | E50: =E17-D17 -> 692 | F50: =F17-E17 -> 1416 | G50: =G17-F17 -> 46817 | H50: =H17-G17 -> 607 | I50: =I17-H17 -> 1065 | J50: =J17-I17 -> 1739 | ... P50: =P17-O17 -> 1313.4983
A56: Column1 | B56: Column2 | C56: Column3 | D56: Column4 | E56: Column5 | F56: Column6 | G56: Column7 | H56: Column8 | I56: Column9 | J56: Column10 | K56: Column11 | L56: Column12 | M56: Column13 | N56: Column14 | O56: Column15 | P56: Column16 | Q56: Column17
A57: Profit and Loss Account
A58: Year | B58: 2016 | C58: 2017 | D58: 2018 | E58: 2019 | F58: 2020 | G58: 2021 | H58: 2022 | I58: 2023 | J58: 2024 | K58: 2025 | L58: 2026 | M58: 2027 | N58: 2028 | O58: 2029 | P58: 2030 | Q58: GROWTH %
A59: INCOME :
A60: Sales Turnover | B60: 33491 | C60: 34487 | D60: 35218 | E60: 38224 | F60: 38785 | G60: 45996 | H60: 51193 | I60: 59144 | J60: 60469 | K60: 61469 | L60: =K60*(1+$Q$61) -> 65868.346 | M60: =L60*(1+$Q$61) -> 70582.555 | N60: =M60*(1+$Q$61) -> 75634.16 | O60: =N60*(1+$Q$61) -> 81047.309 | P60: =O60*(1+$Q$61) -> 86847.878
A61: YOY | C61: =(C60-B60)/B60 -> 0.029739333 | D61: =(D60-C60)/C60 -> 0.021196393 | E61: =(E60-D60)/D60 -> 0.08535408 | F61: =(F60-E60)/E60 -> 0.014676643 | G61: =(G60-F60)/F60 -> 0.18592239 | H61: =(H60-G60)/G60 -> 0.11298809 | I61: =(I60-H60)/H60 -> 0.1553142 | J61: =(J60-I60)/I60 -> 0.022402949 | K61: =(K60-J60)/J60 -> 0.016537399 | Q61: =AVERAGE(B61:K61) -> 0.071570164
A62: Excise Duty | B62: 2430 | C62: 2597 | D62: 693 | E62: 0 | F62: 0 | G62: 0 | H62: 0 | I62: 0 | J62: 0 | K62: 0
A63: Net Sales | B63: 31061 | C63: 31890 | D63: 34525 | E63: 38224 | F63: 38785 | G63: 45996 | H63: 51193 | I63: 59144 | J63: 60469 | K63: 61469
A64: Other Income | B64: 674 | C64: 824 | D64: 625 | E64: 664 | F64: 805 | G64: 630 | H64: 571 | I64: 815 | J64: 1073 | K64: 1777 | L64: =K64*(1+$Q$67) -> 1922.1144 | M64: =L64*(1+$Q$67) -> 2079.0793 | N64: =M64*(1+$Q$67) -> 2248.8623 | O64: =N64*(1+$Q$67) -> 2432.5102 | P64: =O64*(1+$Q$67) -> 2631.1553
A65: Stock Adjustments | B65: -87 | C65: -156 | D65: 71 | E65: -12 | F65: 121 | G65: 391 | H65: 19 | I65: 53 | J65: 8 | K65: 106 | L65: =K65*(1+$Q$67) -> 114.65624 | M65: =L65*(1+$Q$67) -> 124.01936 | N65: =M65*(1+$Q$67) -> 134.1471 | O65: =N65*(1+$Q$67) -> 145.1019 | P65: =O65*(1+$Q$67) -> 156.9513
A66: Total Income | B66: 31648 | C66: 32558 | D66: 35221 | E66: 38876 | F66: 39711 | G66: 47017 | H66: 51783 | I66: 60012 | J66: 61550 | K66: 63352 | L66: =K66*(1+$Q$67) -> 68525.489 | M66: =L66*(1+$Q$67) -> 74121.458 | N66: =M66*(1+$Q$67) -> 80174.409 | O66: =N66*(1+$Q$67) -> 86721.659 | P66: =O66*(1+$Q$67) -> 93803.575
A67: YOY | C67: =(C66-B66)/B66 -> 0.028753792 | D67: =(D66-C66)/C66 -> 0.081792493 | E67: =(E66-D66)/D66 -> 0.10377332 | F67: =(F66-E66)/E66 -> 0.021478547 | G67: =(G66-F66)/F66 -> 0.18397925 | H67: =(H66-G66)/G66 -> 0.10136759 | I67: =(I66-H66)/H66 -> 0.15891316 | J67: =(J66-I66)/I66 -> 0.025628208 | K67: =(K66-J66)/J66 -> 0.029277011 | Q67: =AVERAGE(C67:K67) -> 0.081662596
A68: EXPENDITURE :
A69: Raw Materials | B69: 12847 | C69: 13165 | D69: 13859 | E69: 15430 | F69: 15378 | G69: 19784 | H69: 22398 | I69: 28042 | J69: 26598 | K69: 27187 | L69: =K69*(1+$Q$70) -> 29690.414 | M69: =L69*(1+$Q$70) -> 32424.345 | N69: =M69*(1+$Q$70) -> 35410.021 | O69: =N69*(1+$Q$70) -> 38670.621 | P69: =O69*(1+$Q$70) -> 42231.462
A70: YOY | C70: =(C69-B69)/B69 -> 0.024752861 | D70: =(D69-C69)/C69 -> 0.052715534 | E70: =(E69-D69)/D69 -> 0.11335594 | F70: =(F69-E69)/E69 -> -0.0033700583 | G70: =(G69-F69)/F69 -> 0.2865132 | H70: =(H69-G69)/G69 -> 0.13212697 | I70: =(I69-H69)/H69 -> 0.25198678 | J70: =(J69-I69)/I69 -> -0.051494187 | K70: =(K69-J69)/J69 -> 0.022144522 | Q70: =AVERAGE(C70:K70) -> 0.092081285
A71: Power & Fuel Cost | B71: 271 | C71: 257 | D71: 259 | E71: 269 | F71: 263 | G71: 304 | H71: 277 | I71: 325 | J71: 384 | K71: 365 | L71: =K71*(1+$Q$77) -> 392.10944 | M71: =L71*(1+$Q$77) -> 421.23235 | N71: =M71*(1+$Q$77) -> 452.5183 | O71: =N71*(1+$Q$77) -> 486.12793 | P71: =O71*(1+$Q$77) -> 522.23383
A72: Employee Cost | B72: 1573 | C72: 1620 | D72: 1745 | E72: 1747 | F72: 1691 | G72: 2229 | H72: 2399 | I72: 2665 | J72: 2782 | K72: 2840 | L72: =K72*(1+$Q$77) -> 3050.9337 | M72: =L72*(1+$Q$77) -> 3277.5339 | N72: =M72*(1+$Q$77) -> 3520.9643 | O72: =N72*(1+$Q$77) -> 3782.4749 | P72: =O72*(1+$Q$77) -> 4063.4085
A73: Other Manufacturing Expenses | B73: 2822 | C73: 2771 | D73: 2958 | E73: 3018 | F73: 2860 | G73: 2847 | H73: 3329 | I73: 3705 | J73: 3293 | K73: 3655 | L73: =K73*(1+$Q$77) -> 3926.4657 | M73: =L73*(1+$Q$77) -> 4218.0938 | N73: =M73*(1+$Q$77) -> 4531.3819 | O73: =N73*(1+$Q$77) -> 4867.9386 | P73: =O73*(1+$Q$77) -> 5229.4922
A74: Selling and Administration Expenses | B74: 6500 | C74: 6508 | D74: 7105 | E74: 7645 | F74: 7523 | G74: 7783 | H74: 8046 | I74: 8674 | J74: 10562 | K74: 10364 | L74: =K74*(1+$Q$77) -> 11133.759 | M74: =L74*(1+$Q$77) -> 11960.691 | N74: =M74*(1+$Q$77) -> 12849.04 | O74: =N74*(1+$Q$77) -> 13803.37 | P74: =O74*(1+$Q$77) -> 14828.579
A75: Miscellaneous Expenses | B75: 1353 | C75: 1423 | D75: 1512 | E75: 1693 | F75: 1860 | G75: 2460 | H75: 2472 | I75: 2391 | J75: 2857 | K75: 3053 | L75: =K75*(1+$Q$77) -> 3279.7537 | M75: =L75*(1+$Q$77) -> 3523.349 | N75: =M75*(1+$Q$77) -> 3785.0366 | O75: =N75*(1+$Q$77) -> 4066.1605 | P75: =O75*(1+$Q$77) -> 4368.1641
A76: Total Expenditure | B76: 25366 | C76: 25744 | D76: 27438 | E76: 29802 | F76: 29575 | G76: 35407 | H76: 38921 | I76: 45802 | J76: 46476 | K76: 47464 | L76: =K76*(1+$Q$77) -> 50989.266 | M76: =L76*(1+$Q$77) -> 54776.363 | N76: =M76*(1+$Q$77) -> 58844.736 | O76: =N76*(1+$Q$77) -> 63215.277 | P76: =O76*(1+$Q$77) -> 67910.429
A77: YOY | C77: =(C76-B76)/B76 -> 0.014901837 | D77: =(D76-C76)/C76 -> 0.06580174 | E77: =(E76-D76)/D76 -> 0.086157883 | F77: =(F76-E76)/E76 -> -0.0076169385 | G77: =(G76-F76)/F76 -> 0.19719358 | H77: =(H76-G76)/G76 -> 0.099245912 | I77: =(I76-H76)/H76 -> 0.17679402 | J77: =(J76-I76)/I76 -> 0.014715515 | K77: =(K76-J76)/J76 -> 0.021258284 | Q77: =AVERAGE(C77:K77) -> 0.074272425
A78: Operating Profit | B78: 6282 | C78: 6814 | D78: 7783 | E78: 9074 | F78: 10136 | G78: 11610 | H78: 12862 | I78: 14210 | J78: 15074 | K78: 15888 | L78: =K78*(1+$Q$79) -> 17622.746 | M78: =L78*(1+$Q$79) -> 19546.902 | N78: =M78*(1+$Q$79) -> 21681.149 | O78: =N78*(1+$Q$79) -> 24048.425 | P78: =O78*(1+$Q$79) -> 26674.174
A79: YOY | C79: =(C78-B78)/B78 -> 0.084686406 | D79: =(D78-C78)/C78 -> 0.14220722 | E79: =(E78-D78)/D78 -> 0.16587434 | F79: =(F78-E78)/E78 -> 0.11703769 | G79: =(G78-F78)/F78 -> 0.14542226 | H79: =(H78-G78)/G78 -> 0.10783807 | I79: =(I78-H78)/H78 -> 0.10480485 | J79: =(J78-I78)/I78 -> 0.060802252 | K79: =(K78-J78)/J78 -> 0.054000265 | Q79: =AVERAGE(C79:K79) -> 0.10918593
A80: Interest | B80: 15 | C80: 22 | D80: 20 | E80: 28 | F80: 106 | G80: 108 | H80: 98 | I80: 101 | J80: 302 | K80: 364 | L80: =K80*($Q$81+1) -> 595.08971 | M80: =L80*($Q$81+1) -> 972.88944 | N80: =M80*($Q$81+1) -> 1590.5398 | O80: =N80*($Q$81+1) -> 2600.3128 | P80: =O80*($Q$81+1) -> 4251.1522
A81: YOY | C81: =(C80-B80)/B80 -> 0.46666667 | D81: =(D80-C80)/C80 -> -0.090909091 | E81: =(E80-D80)/D80 -> 0.4 | F81: =(F80-E80)/E80 -> 2.7857143 | G81: =(G80-F80)/F80 -> 0.018867925 | H81: =(H80-G80)/G80 -> -0.092592593 | I81: =(I80-H80)/H80 -> 0.030612245 | J81: =(J80-I80)/I80 -> 1.990099 | K81: =(K80-J80)/J80 -> 0.20529801 | Q81: =AVERAGE(C81:K81) -> 0.63486183
A82: Gross Profit | B82: 6267 | C82: 6792 | D82: 7763 | E82: 9046 | F82: 10030 | G82: 11502 | H82: 12764 | I82: 14109 | J82: 14772 | K82: 15524
A83: Depreciation | B83: 321 | C83: 396 | D83: 478 | E83: 524 | F83: 938 | G83: 1012 | H83: 1025 | I83: 1030 | J83: 1097 | K83: 1224 | L83: =K83*(1+$Q$84) -> 1442.2066 | M83: =L83*(1+$Q$84) -> 1699.3136 | N83: =M83*(1+$Q$84) -> 2002.2559 | O83: =N83*(1+$Q$84) -> 2359.2048 | P83: =O83*(1+$Q$84) -> 2779.7882
A84: YOY | C84: =(C83-B83)/B83 -> 0.23364486 | D84: =(D83-C83)/C83 -> 0.20707071 | E84: =(E83-D83)/D83 -> 0.09623431 | F84: =(F83-E83)/E83 -> 0.79007634 | G84: =(G83-F83)/F83 -> 0.078891258 | H84: =(H83-G83)/G83 -> 0.01284585 | I84: =(I83-H83)/H83 -> 0.0048780488 | J84: =(J83-I83)/I83 -> 0.065048544 | K84: =(K83-J83)/J83 -> 0.11577028 | Q84: =AVERAGE(C84:K84) -> 0.17827336
A85: Profit Before Tax | B85: 5946 | C85: 6396 | D85: 7285 | E85: 8522 | F85: 9092 | G85: 10490 | H85: 11739 | I85: 13079 | J85: 13675 | K85: 14300 | L85: =K85*(1+$Q$86) -> 15777.048 | M85: =L85*(1+$Q$86) -> 17406.661 | N85: =M85*(1+$Q$86) -> 19204.596 | O85: =N85*(1+$Q$86) -> 21188.24 | P85: =O85*(1+$Q$86) -> 23376.776
A86: YOY | C86: =(C85-B85)/B85 -> 0.07568113 | D86: =(D85-C85)/C85 -> 0.13899312 | E86: =(E85-D85)/D85 -> 0.16980096 | F86: =(F85-E85)/E85 -> 0.066885708 | G86: =(G85-F85)/F85 -> 0.15376155 | H86: =(H85-G85)/G85 -> 0.11906578 | I86: =(I85-H85)/H85 -> 0.11414942 | J86: =(J85-I85)/I85 -> 0.045569233 | K86: =(K85-J85)/J85 -> 0.045703839 | Q86: =AVERAGE(C86:K86) -> 0.10329008
A87: Tax | B87: 1816 | C87: 1865 | D87: 2148 | E87: 2565 | F87: 2202 | G87: 2458 | H87: 2778 | I87: 2922 | J87: 3446 | K87: 3525
A88: Deferred Tax | B88: -7 | C88: 41 | D88: -100 | E88: -79 | F88: 152 | G88: 78 | H88: 143 | I88: 195 | J88: 115 | K88: 131
A89: Reported Net Profit | B89: 4137 | C89: 4490 | D89: 5237 | E89: 6036 | F89: 6738 | G89: 7954 | H89: 8818 | I89: 9962 | J89: 10114 | K89: 10644 | L89: =K89*(1+$Q$90) -> 11835.012 | M89: =L89*(1+$Q$90) -> 13159.293 | N89: =M89*(1+$Q$90) -> 14631.754 | O89: =N89*(1+$Q$90) -> 16268.977 | P89: =O89*(1+$Q$90) -> 18089.396
A90: YOY | C90: =(C89-B89)/B89 -> 0.085327532 | D90: =(D89-C89)/C89 -> 0.16636971 | E90: =(E89-D89)/D89 -> 0.15256826 | F90: =(F89-E89)/E89 -> 0.11630219 | G90: =(G89-F89)/F89 -> 0.18046898 | H90: =(H89-G89)/G89 -> 0.10862459 | I90: =(I89-H89)/H89 -> 0.12973463 | J90: =(J89-I89)/I89 -> 0.01525798 | K90: =(K89-J89)/J89 -> 0.05240261 | Q90: =AVERAGE(C90:K90) -> 0.11189517
A91: Extraordinary Items | B91: -21.53 | C91: 96.46 | D91: -42.51 | E91: -155.45 | F91: -145.99 | G91: -172.12 | H91: -25.54 | I91: -47.22 | J91: -65.82 | K91: 314.11
A92: Adjusted Net Profit | B92: 4158.53 | C92: 4393.54 | D92: 5279.51 | E92: 6191.45 | F92: 6883.99 | G92: 8126.12 | H92: 8843.54 | I92: 10009.22 | J92: 10179.82 | K92: 10329.89
A93: Adjst. below Net Profit | B93: 255 | C93: -693 | D93: -755 | E93: -534 | F93: -1134 | G93: -2 | H93: 31 | I93: -13 | J93: 27 | K93: -17
A94: P & L Balance brought forward | B94: 3599 | C94: 3727 | D94: 3953 | E94: 4539 | F94: 7303 | G94: 7664 | H94: 6805 | I94: 8135 | J94: 9625 | K94: 10368
A95: Appropriations | B95: 4264 | C95: 3571 | D95: 3896 | E95: 2738 | F95: 5243 | G95: 8811 | H95: 7519 | I95: 8459 | J95: 9398 | K95: 12453
A96: P & L Balance carried down | B96: 3727 | C96: 3953 | D96: 4539 | E96: 7303 | F96: 7664 | G96: 6805 | H96: 8135 | I96: 9625 | J96: 10368 | K96: 8542
A97: Dividend | B97: 3571 | C97: 3679 | D97: 4329 | E97: 1948 | F97: 0 | G97: 0 | H97: 0 | I97: 0 | J97: 0 | K97: 0
A98: Equity Dividend % | B98: 1600 | C98: 1700 | D98: 2000 | E98: 2200 | F98: 2500 | G98: 4050 | H98: 3400 | I98: 3900 | J98: 4200 | K98: 5300
A99: Dividend Per Share(Rs) | B99: 16 | C99: 17 | D99: 20 | E99: 22 | F99: 25 | G99: 40.5 | H99: 34 | I99: 39 | J99: 42 | K99: 53
A100: Earnings Per Share-Unit Curr | B100: 19.15 | C100: 20.79 | D100: 24.25 | E100: 27.94 | F100: 31.19 | G100: 33.85 | H100: 37.52 | I100: 42.39 | J100: 43.04 | K100: 45.29
A101: Earnings Per Share(Adj)-Unit Curr | B101: 18.84 | C101: 20.45 | D101: 23.85 | E101: 27.48 | F101: 30.68 | G101: 33.3 | H101: 36.91 | I101: 41.7 | J101: 42.34 | K101: 44.55 | L101: =K101*(1+$Q$102) -> 49.061879 | M101: =L101*(1+$Q$102) -> 54.030706 | N101: =M101*(1+$Q$102) -> 59.502759 | O101: =N101*(1+$Q$102) -> 65.529005 | P101: =O101*(1+$Q$102) -> 72.165569
A102: YOY | C102: =(C101-B101)/B101 -> 0.085456476 | D102: =(D101-C101)/C101 -> 0.16625917 | E102: =(E101-D101)/D101 -> 0.15220126 | F102: =(F101-E101)/E101 -> 0.11644833 | G102: =(G101-F101)/F101 -> 0.085397653 | H102: =(H101-G101)/G101 -> 0.10840841 | I102: =(I101-H101)/H101 -> 0.12977513 | J102: =(J101-I101)/I101 -> 0.015347722 | K102: =(K101-J101)/J101 -> 0.052196504 | Q102: =AVERAGE(C102:K102) -> 0.10127674
A103: Book Value-Unit Curr | B103: 29.07 | C103: 30.05 | D103: 32.75 | E103: 35.46 | F103: 37.18 | G103: 201.85 | H103: 207.49 | I103: 213.71 | J103: 216.91 | K103: 209.16
A104: Book Value(Adj)-Unit Curr | B104: 28.6 | C104: 29.56 | D104: 32.22 | E104: 34.88 | F104: 36.57 | G104: 198.55 | H104: 204.1 | I104: 210.22 | J104: 213.37 | K104: 205.74
A105: Dividend Per Share Adj.(Rs) | B105: 15.74 | C105: 16.72 | D105: 19.67 | E105: 21.64 | F105: 24.59 | G105: 39.84 | H105: 33.44 | I105: 38.36 | J105: 41.31 | K105: 52.13
A106: tax rate | B106: =B87/B85 -> 0.30541541 | C106: =C87/C85 -> 0.29158849 | D106: =D87/D85 -> 0.29485244 | E106: =E87/E85 -> 0.30098568 | F106: =F87/F85 -> 0.24219094 | G106: =G87/G85 -> 0.2343184 | H106: =H87/H85 -> 0.23664707 | I106: =I87/I85 -> 0.22341158 | ... K106: =K87/K85 -> 0.2465035 | Q106: =AVERAGE(B106:K106) -> 0.26279062
A107: COGS | B107: =B69+B71+B73 -> 15940 | C107: =C69+C71+C73 -> 16193 | D107: =D69+D71+D73 -> 17076 | E107: =E69+E71+E73 -> 18717 | F107: =F69+F71+F73 -> 18501 | G107: =G69+G71+G73 -> 22935 | H107: =H69+H71+H73 -> 26004 | I107: =I69+I71+I73 -> 32072 | ... P107: =P69+P71+P73 -> 47983.188
A108: EBIT | B108: =B85+B80 -> 5961 | C108: =C85+C80 -> 6418 | D108: =D85+D80 -> 7305 | E108: =E85+E80 -> 8550 | F108: =F85+F80 -> 9198 | G108: =G85+G80 -> 10598 | H108: =H85+H80 -> 11837 | I108: =I85+I80 -> 13180 | ... P108: =P85+P80 -> 27627.928
...

Sheet HUL Financial statement
A1: Particulars | B1: 2016 | C1: 2017 | D1: 2018 | E1: 2019 | F1: 2020 | G1: 2021 | H1: 2022 | I1: 2023 | J1: 2024 | K1: 2025 | L1: 2026F | M1: 2027F | N1: 2028F | O1: 2029F | P1: 2030F | Q1: Growth %
A2: SOURCES OF FUNDS
A3: Share Capital | B3: 216 | C3: 216 | D3: 216 | E3: 216 | F3: 216 | G3: 235 | H3: 235 | I3: 235 | J3: 235 | K3: 235
A4: Reserves | B4: 6063 | C4: 6274 | D4: 6859 | E4: 7443 | F4: 7815 | G4: 47199 | H4: 48525 | I4: 49986 | J4: 50738 | K4: 48918
A5: Total Shareholders Funds | B5: 6279 | C5: 6490 | D5: 7075 | E5: 7659 | F5: 8031 | G5: 47434 | H5: 48760 | I5: 50221 | J5: 50973 | K5: 49153
A6: Total Debt | B6: 0 | C6: 0 | D6: 0 | E6: 0 | F6: 0 | G6: 943 | H6: 971 | I6: 1039 | J6: 1374 | K6: 1537
A7: Other Liabilities | B7: 989 | C7: 1059 | D7: 1438 | E7: 1853 | F7: 2467 | G7: 3176 | H7: 3206 | I7: 2906 | J7: 6212 | K7: 5748
A8: Total Liabilities | B8: 7268 | C8: 7549 | D8: 8513 | E8: 9512 | F8: 10498 | G8: 51553 | H8: 52937 | I8: 54166 | J8: 58559 | K8: 56438
A9: APPLICATION OF FUNDS
A10: Gross Block | B10: 3218 | C10: 4712 | D10: 5267 | E10: 5959 | F10: 7375 | G10: 54192 | H10: 54799 | I10: 55864 | J10: 57603 | K10: 58790
A11: Less: Accumulated Depreciation | B11: 304 | C11: 688 | D11: 1125 | E11: 1616 | F11: 2319 | G11: 3165 | H11: 3765 | I11: 4459 | J11: 5224 | K11: 5883
A12: Net Block | B12: 2914 | C12: 4024 | D12: 4142 | E12: 4343 | F12: 5056 | G12: 51027 | H12: 51034 | I12: 51405 | J12: 52379 | K12: 52907
A13: Capital Work in Progress | B13: 386 | C13: 203 | D13: 430 | E13: 373 | F13: 513 | G13: 623 | H13: 901 | I13: 1020 | J13: 915 | K13: 956
A14: Investments | B14: 2780 | C14: 3779 | D14: 3111 | E14: 2949 | F14: 1500 | G14: 2995 | H14: 4122 | I14: 3794 | J14: 5493 | K14: 4602
A15: CURRENT ASSETS
A16: Inventory | B16: 2528 | C16: 2362 | D16: 2359 | E16: 2422 | F16: 2636 | G16: 3383 | H16: 3890 | I16: 4031 | J16: 3812 | K16: 4161
A17: Sundry Debtors | B17: 1064 | C17: 928 | D17: 1147 | E17: 1673 | F17: 1046 | G17: 1648 | H17: 1932 | I17: 2735 | J17: 2690 | K17: 3450
A18: Cash & Bank | B18: 2759 | C18: 1671 | D18: 3373 | E18: 3688 | F18: 5017 | G18: 4321 | H18: 3618 | I18: 4422 | J18: 7216 | K18: 7293
A19: Loans & Advances | B19: 740 | C19: 885 | D19: 1405 | E19: 898 | F19: 1961 | G19: 1605 | H19: 1697 | I19: 2050 | J19: 2068 | K19: 2381
A20: Total Current Assets | B20: 7091 | C20: 5846 | D20: 8284 | E20: 8681 | F20: 10660 | G20: 10957 | H20: 11137 | I20: 13238 | J20: 15786 | K20: 17285
A21: CURRENT LIABILITIES
A22: Current Liabilities | B22: 6362 | C22: 6815 | D22: 7985 | E22: 7852 | F22: 8686 | G22: 10086 | H22: 10325 | I22: 10955 | J22: 11734 | K22: 12744
A23: Provisions | B23: 290 | C23: 387 | D23: 651 | E23: 501 | F23: 418 | G23: 491 | H23: 334 | I23: 379 | J23: 329 | K23: 2548
A24: Total Current Liabilities | B24: 6652 | C24: 7202 | D24: 8636 | E24: 8353 | F24: 9104 | G24: 10577 | H24: 10659 | I24: 11334 | J24: 12063 | K24: 15292
A32: Profit and Loss Statement
A34: Particulars | B34: 2016 | C34: 2017 | D34: 2018 | E34: 2019 | F34: 2020 | G34: 2021 | H34: 2022 | I34: 2023 | J34: 2024 | K34: 2025 | L34: 2026F | M34: 2027F | N34: 2028F | O34: 2029F | P34: 2030F | Q34: GROWTH
A35: Revenue from Operations | B35: ='HUL ASSUMPTION '!B60 -> 33491 | C35: ='HUL ASSUMPTION '!C60 -> 34487 | D35: ='HUL ASSUMPTION '!D60 -> 35218 | E35: ='HUL ASSUMPTION '!E60 -> 38224 | F35: ='HUL ASSUMPTION '!F60 -> 38785 | G35: ='HUL ASSUMPTION '!G60 -> 45996 | H35: ='HUL ASSUMPTION '!H60 -> 51193 | I35: ='HUL ASSUMPTION '!I60 -> 59144 | ... P35: ='HUL ASSUMPTION '!P60 -> 86847.878
A36: Other revenues | B36: ='HUL ASSUMPTION '!B64 -> 674 | C36: ='HUL ASSUMPTION '!C64 -> 824 | D36: ='HUL ASSUMPTION '!D64 -> 625 | E36: ='HUL ASSUMPTION '!E64 -> 664 | F36: ='HUL ASSUMPTION '!F64 -> 805 | G36: ='HUL ASSUMPTION '!G64 -> 630 | H36: ='HUL ASSUMPTION '!H64 -> 571 | I36: ='HUL ASSUMPTION '!I64 -> 815 | ... P36: ='HUL ASSUMPTION '!P64 -> 2631.1553
A37: Revenue | B37: =SUM(B35:B36) -> 34165 | C37: =SUM(C35:C36) -> 35311 | D37: =SUM(D35:D36) -> 35843 | E37: =SUM(E35:E36) -> 38888 | F37: =SUM(F35:F36) -> 39590 | G37: =SUM(G35:G36) -> 46626 | H37: =SUM(H35:H36) -> 51764 | I37: =SUM(I35:I36) -> 59959 | ... P37: =SUM(P35:P36) -> 89479.034
A39: Cost of Material Consumed | B39: ='HUL ASSUMPTION '!B69 -> 12847 | C39: ='HUL ASSUMPTION '!C69 -> 13165 | D39: ='HUL ASSUMPTION '!D69 -> 13859 | E39: ='HUL ASSUMPTION '!E69 -> 15430 | F39: ='HUL ASSUMPTION '!F69 -> 15378 | G39: ='HUL ASSUMPTION '!G69 -> 19784 | H39: ='HUL ASSUMPTION '!H69 -> 22398 | I39: ='HUL ASSUMPTION '!I69 -> 28042 | ... P39: ='HUL ASSUMPTION '!P69 -> 42231.462
A40: Changes In Inventories Of FG,WIP And Stock-In Trade | B40: ='HUL ASSUMPTION '!B65 -> -87 | C40: ='HUL ASSUMPTION '!C65 -> -156 | D40: ='HUL ASSUMPTION '!D65 -> 71 | E40: ='HUL ASSUMPTION '!E65 -> -12 | F40: ='HUL ASSUMPTION '!F65 -> 121 | G40: ='HUL ASSUMPTION '!G65 -> 391 | H40: ='HUL ASSUMPTION '!H65 -> 19 | I40: ='HUL ASSUMPTION '!I65 -> 53 | ... P40: ='HUL ASSUMPTION '!P65 -> 156.9513
A41: Cost of Goods sold | B41: =SUM(B39:B40) -> 12760 | C41: =SUM(C39:C40) -> 13009 | D41: =SUM(D39:D40) -> 13930 | E41: =SUM(E39:E40) -> 15418 | F41: =SUM(F39:F40) -> 15499 | G41: =SUM(G39:G40) -> 20175 | H41: =SUM(H39:H40) -> 22417 | I41: =SUM(I39:I40) -> 28095 | ... P41: =SUM(P39:P40) -> 42388.413
A42: Gross Margin | B42: =B37-B41 -> 21405 | C42: =C37-C41 -> 22302 | D42: =D37-D41 -> 21913 | E42: =E37-E41 -> 23470 | F42: =F37-F41 -> 24091 | G42: =G37-G41 -> 26451 | H42: =H37-H41 -> 29347 | I42: =I37-I41 -> 31864 | ... P42: =P37-P41 -> 47090.621
A44: Employee Benefit Expenses | B44: ='HUL ASSUMPTION '!B72 -> 1573 | C44: ='HUL ASSUMPTION '!C72 -> 1620 | D44: ='HUL ASSUMPTION '!D72 -> 1745 | E44: ='HUL ASSUMPTION '!E72 -> 1747 | F44: ='HUL ASSUMPTION '!F72 -> 1691 | G44: ='HUL ASSUMPTION '!G72 -> 2229 | H44: ='HUL ASSUMPTION '!H72 -> 2399 | I44: ='HUL ASSUMPTION '!I72 -> 2665 | ... P44: ='HUL ASSUMPTION '!P72 -> 4063.4085
A45: Other Expenses | B45: ='HUL ASSUMPTION '!B74+'HUL ASSUMPTION '!B75 -> 7853 | C45: ='HUL ASSUMPTION '!C74+'HUL ASSUMPTION '!C75 -> 7931 | D45: ='HUL ASSUMPTION '!D74+'HUL ASSUMPTION '!D75 -> 8617 | E45: ='HUL ASSUMPTION '!E74+'HUL ASSUMPTION '!E75 -> 9338 | F45: ='HUL ASSUMPTION '!F74+'HUL ASSUMPTION '!F75 -> 9383 | G45: ='HUL ASSUMPTION '!G74+'HUL ASSUMPTION '!G75 -> 10243 | H45: ='HUL ASSUMPTION '!H74+'HUL ASSUMPTION '!H75 -> 10518 | I45: ='HUL ASSUMPTION '!I74+'HUL ASSUMPTION '!I75 -> 11065 | ... P45: ='HUL ASSUMPTION '!P74+'HUL ASSUMPTION '!P75 -> 19196.743
A46: TOTAL OPERATING EXPENSES | B46: =B44+B45 -> 9426 | C46: =C44+C45 -> 9551 | D46: =D44+D45 -> 10362 | E46: =E44+E45 -> 11085 | F46: =F44+F45 -> 11074 | G46: =G44+G45 -> 12472 | H46: =H44+H45 -> 12917 | I46: =I44+I45 -> 13730 | ... P46: =P44+P45 -> 23260.152
A47: EBITDA | B47: =B42-B46 -> 11979 | C47: =C42-C46 -> 12751 | D47: =D42-D46 -> 11551 | E47: =E42-E46 -> 12385 | F47: =F42-F46 -> 13017 | G47: =G42-G46 -> 13979 | H47: =H42-H46 -> 16430 | I47: =I42-I46 -> 18134 | ... P47: =P42-P46 -> 23830.469
A49: Depreciation And Amortisation Expenses | B49: ='HUL ASSUMPTION '!B83 -> 321 | C49: ='HUL ASSUMPTION '!C83 -> 396 | D49: ='HUL ASSUMPTION '!D83 -> 478 | E49: ='HUL ASSUMPTION '!E83 -> 524 | F49: ='HUL ASSUMPTION '!F83 -> 938 | G49: ='HUL ASSUMPTION '!G83 -> 1012 | H49: ='HUL ASSUMPTION '!H83 -> 1025 | I49: ='HUL ASSUMPTION '!I83 -> 1030 | ... P49: ='HUL ASSUMPTION '!P83 -> 2779.7882
A50: EBIT | B50: =B47-B49 -> 11658 | C50: =C47-C49 -> 12355 | D50: =D47-D49 -> 11073 | E50: =E47-E49 -> 11861 | F50: =F47-F49 -> 12079 | G50: =G47-G49 -> 12967 | H50: =H47-H49 -> 15405 | I50: =I47-I49 -> 17104 | ... P50: =P47-P49 -> 21050.681
A52: Finance Cost | B52: ='HUL ASSUMPTION '!B80 -> 15 | C52: ='HUL ASSUMPTION '!C80 -> 22 | D52: ='HUL ASSUMPTION '!D80 -> 20 | E52: ='HUL ASSUMPTION '!E80 -> 28 | F52: ='HUL ASSUMPTION '!F80 -> 106 | G52: ='HUL ASSUMPTION '!G80 -> 108 | H52: ='HUL ASSUMPTION '!H80 -> 98 | I52: ='HUL ASSUMPTION '!I80 -> 101 | ... P52: ='HUL ASSUMPTION '!P80 -> 4251.1522
A53: EBT | B53: =B50-B52 -> 11643 | C53: =C50-C52 -> 12333 | D53: =D50-D52 -> 11053 | E53: =E50-E52 -> 11833 | F53: =F50-F52 -> 11973 | G53: =G50-G52 -> 12859 | H53: =H50-H52 -> 15307 | I53: =I50-I52 -> 17003 | ... P53: =P50-P52 -> 16799.529
A54: Tax Rate | B54: ='HUL ASSUMPTION '!B106 -> 0.30541541 | C54: ='HUL ASSUMPTION '!C106 -> 0.29158849 | D54: ='HUL ASSUMPTION '!D106 -> 0.29485244 | E54: ='HUL ASSUMPTION '!E106 -> 0.30098568 | F54: ='HUL ASSUMPTION '!F106 -> 0.24219094 | G54: ='HUL ASSUMPTION '!G106 -> 0.2343184 | H54: ='HUL ASSUMPTION '!H106 -> 0.23664707 | I54: ='HUL ASSUMPTION '!I106 -> 0.22341158 | ... P54: ='HUL ASSUMPTION '!P106 -> 0
A55: Current Tax | B55: ='HUL ASSUMPTION '!B87 -> 1816 | C55: ='HUL ASSUMPTION '!C87 -> 1865 | D55: ='HUL ASSUMPTION '!D87 -> 2148 | E55: ='HUL ASSUMPTION '!E87 -> 2565 | F55: ='HUL ASSUMPTION '!F87 -> 2202 | G55: ='HUL ASSUMPTION '!G87 -> 2458 | H55: ='HUL ASSUMPTION '!H87 -> 2778 | I55: ='HUL ASSUMPTION '!I87 -> 2922 | ... P55: ='HUL ASSUMPTION '!P87 -> 0
A56: Deferred Tax | B56: ='HUL ASSUMPTION '!B88 -> -7 | C56: ='HUL ASSUMPTION '!C88 -> 41 | D56: ='HUL ASSUMPTION '!D88 -> -100 | E56: ='HUL ASSUMPTION '!E88 -> -79 | F56: ='HUL ASSUMPTION '!F88 -> 152 | G56: ='HUL ASSUMPTION '!G88 -> 78 | H56: ='HUL ASSUMPTION '!H88 -> 143 | I56: ='HUL ASSUMPTION '!I88 -> 195 | ... P56: ='HUL ASSUMPTION '!P88 -> 0
A57: Net Income | B57: =B53-B55-B56 -> 9834 | C57: =C53-C55-C56 -> 10427 | D57: =D53-D55-D56 -> 9005 | E57: =E53-E55-E56 -> 9347 | F57: =F53-F55-F56 -> 9619 | G57: =G53-G55-G56 -> 10323 | H57: =H53-H55-H56 -> 12386 | I57: =I53-I55-I56 -> 13886 | ... P57: =P53-P55-P56 -> 16799.529
A58: EPS | B58: ='HUL ASSUMPTION '!B101 -> 18.84 | C58: ='HUL ASSUMPTION '!C101 -> 20.45 | D58: ='HUL ASSUMPTION '!D101 -> 23.85 | E58: ='HUL ASSUMPTION '!E101 -> 27.48 | F58: ='HUL ASSUMPTION '!F101 -> 30.68 | G58: ='HUL ASSUMPTION '!G101 -> 33.3 | H58: ='HUL ASSUMPTION '!H101 -> 36.91 | I58: ='HUL ASSUMPTION '!I101 -> 41.7 | ... P58: ='HUL ASSUMPTION '!P101 -> 72.165569
A59: Dividend | B59: ='HUL ASSUMPTION '!B97 -> 3571 | C59: ='HUL ASSUMPTION '!C97 -> 3679 | D59: ='HUL ASSUMPTION '!D97 -> 4329 | E59: ='HUL ASSUMPTION '!E97 -> 1948 | F59: ='HUL ASSUMPTION '!F97 -> 0 | G59: ='HUL ASSUMPTION '!G97 -> 0 | H59: ='HUL ASSUMPTION '!H97 -> 0 | I59: ='HUL ASSUMPTION '!I97 -> 0 | ... K59: ='HUL ASSUMPTION '!K97 -> 0
A60: Rate of Dividend | B60: =(B59/B57) -> 0.36312792 | C60: =(C59/C57) -> 0.35283399 | D60: =(D59/D57) -> 0.48073293 | E60: =(E59/E57) -> 0.20840912 | F60: =(F59/F57) -> 0 | G60: =(G59/G57) -> 0 | H60: =(H59/H57) -> 0 | I60: =(I59/I57) -> 0 | ... P60: =(P59/P57) -> 0

Sheet PPE ANALYSIS
A1: PPE SCHEDULE | B1: ACTUAL PERIOD | G1: FORECASTED PERIOD
A3: INR in Cr. | B3: 2018 Actual | C3: 2019 Actual | D3: 2020 Actual | E3: 2021 Actual | F3: 2022 Actual | G3: 2023 Forecast | H3: 2024 Forecast | I3: 2025 Forecast | J3: 2026 Forecast | K3: 2027 Forecast
A4: Revenues | B4: ='HUL ASSUMPTION '!B63 -> 31061 | C4: ='HUL ASSUMPTION '!C63 -> 31890 | D4: ='HUL ASSUMPTION '!D63 -> 34525 | E4: ='HUL ASSUMPTION '!E63 -> 38224 | F4: ='HUL ASSUMPTION '!F63 -> 38785 | G4: ='HUL ASSUMPTION '!G63 -> 45996 | H4: ='HUL ASSUMPTION '!H63 -> 51193 | I4: ='HUL ASSUMPTION '!I63 -> 59144 | ... K4: ='HUL ASSUMPTION '!K63 -> 61469
A5: Opening PP&E | C5: 70942.9 | D5: 70416.82 | E5: 66392.35 | F5: 90404.59 | G5: 87946.22 | H5: 89491.881 | I5: 91764.287 | J5: 94551.374 | K5: 97484.683
A6: Capex | B6: ='HUL ASSUMPTION '!B40 -> 168 | C6: ='HUL ASSUMPTION '!C40 -> 160 | D6: ='HUL ASSUMPTION '!D40 -> 255 | E6: ='HUL ASSUMPTION '!E40 -> 339 | F6: ='HUL ASSUMPTION '!F40 -> 261 | G6: ='HUL ASSUMPTION '!G40 -> -5986 | H6: ='HUL ASSUMPTION '!H40 -> -6141 | I6: ='HUL ASSUMPTION '!I40 -> -6325 | ... K6: ='HUL ASSUMPTION '!K40 -> -6583
A7: (% of revenues) | B7: =B6/B4 -> 0.0054087119 | C7: =C6/C4 -> 0.0050172468 | D7: =D6/D4 -> 0.0073859522 | E7: =E6/E4 -> 0.0088687735 | F7: =F6/F4 -> 0.0067294057 | G7: =G6/G4 -> -0.13014175 | H7: =H6/H4 -> -0.11995781 | I7: =I6/I4 -> -0.10694238 | ... K7: =K6/K4 -> -0.10709463
A8: Depreciation | B8: ='HUL ASSUMPTION '!B83 -> 321 | C8: ='HUL ASSUMPTION '!C83 -> 396 | D8: ='HUL ASSUMPTION '!D83 -> 478 | E8: ='HUL ASSUMPTION '!E83 -> 524 | F8: ='HUL ASSUMPTION '!F83 -> 938 | G8: ='HUL ASSUMPTION '!G83 -> 1012 | H8: ='HUL ASSUMPTION '!H83 -> 1025 | I8: ='HUL ASSUMPTION '!I83 -> 1030 | ... K8: ='HUL ASSUMPTION '!K83 -> 1224
A9: (Depreceiation Rate %) | C9: 0.052251862 | D9: 0.05385412 | E9: 0.080995524 | F9: 0.058404745 | G9: 0.061376563 | H9: 0.063657738 | I9: 0.066108642 | J9: 0.062386922 | K9: 0.063382466
A10: Ending PP&E | C10: 70416.82 | D10: 66392.35 | E10: 90404.59 | F10: 87946.22 | G10: 89491.881 | H10: 91764.287 | I10: 94551.374 | J10: 97484.683 | K10: 101963.14

Sheet Beta
A1: Date | B1: HUL | C1: sensex | D1: MARKET RETURN | E1: FIRM RETURN | F1: BETA
A2: 40546 | B2: 313.1 | C2: 20561.05
A3: 40547 | B3: 321.05 | C3: 20498.72 | D3: =LN(C3/C2) -> -0.0030360642 | E3: =LN(B3/B2) -> 0.025074246 | F3: 0.53595125
A4: 40548 | B4: 325.65 | C4: 20301.1 | D4: =LN(C4/C3) -> -0.0096873734 | E4: =LN(B4/B3) -> 0.014226311
A5: 40549 | B5: 320.05 | C5: 20184.74 | D5: =LN(C5/C4) -> -0.0057481984 | E5: =LN(B5/B4) -> -0.017345951
A6: 40550 | B6: 312.25 | C6: 19691.81 | D6: =LN(C6/C5) -> -0.02472406 | E6: =LN(B6/B5) -> -0.024673085
A7: 40553 | B7: 308.25 | C7: 19224.12 | D7: =LN(C7/C6) -> -0.024037073 | E7: =LN(B7/B6) -> -0.012893007
A8: 40554 | B8: 309 | C8: 19196.34 | D8: =LN(C8/C7) -> -0.0014461047 | E8: =LN(B8/B7) -> 0.0024301349
A9: 40555 | B9: 305 | C9: 19534.1 | D9: =LN(C9/C8) -> 0.01744202 | E9: =LN(B9/B8) -> -0.0130295
A10: 40556 | B10: 302.4 | C10: 19182.82 | D10: =LN(C10/C9) -> -0.018146569 | E10: =LN(B10/B9) -> -0.0085611323
A11: 40557 | B11: 302.6 | C11: 18860.44 | D11: =LN(C11/C10) -> -0.01694848 | E11: =LN(B11/B10) -> 0.00066115705
A12: 40560 | B12: 301.65 | C12: 18882.25 | D12: =LN(C12/C11) -> 0.0011557206 | E12: =LN(B12/B11) -> -0.0031443965
A13: 40561 | B13: 301.9 | C13: 19092.05 | D13: =LN(C13/C12) -> 0.011049691 | E13: =LN(B13/B12) -> 0.00082843183
A14: 40562 | B14: 299.8 | C14: 18978.32 | D14: =LN(C14/C13) -> -0.005974743 | E14: =LN(B14/B13) -> -0.006980251
A15: 40563 | B15: 299.65 | C15: 19046.54 | D15: =LN(C15/C14) -> 0.0035881827 | E15: =LN(B15/B14) -> -0.00050045876
... A3720: 46023 | B3720: 2323 | C3720: 85188.6 | D3720: =LN(C3720/C3719) -> -0.00037556658 | E3720: =LN(B3720/B3719) -> 0.003320185

Sheet Historical Beta
A1: Event Window | B1: 1 day
A2: Anticipation Period | B2: 15 days
A3: Adjusted period | B3: 15 days
A4: Estimated window | B4: 30 days
A7: Anticipated period | G7: Adjusted period | M7: Estimated window
A8: Date | B8: HUL | C8: sensex | D8: MARKET RETURN | E8: FIRM RETURN | G8: Date | H8: HUL | I8: sensex | J8: MARKET RETURN | K8: FIRM RETURN | M8: Date | N8: HUL | O8: sensex | P8: MARKET RETURN | Q8: FIRM RETURN
A9: 40830 | B9: 332.1 | C9: 17082.69 | D9: - | E9: - | G9: 40856 | H9: 391.3 | I9: 17362.1 | J9: - | K9: - | M9: 40785 | N9: 320.9 | O9: 16676.75 | P9: - | Q9: -
A10: 40833 | B10: 333.1 | C10: 17025.09 | D10: =LN(C10/C9) -> -0.0033775317 | E10: =LN(B10/B9) -> 0.0030066168 | G10: 40858 | H10: 396.15 | I10: 17192.82 | J10: =LN(I10/I9) -> -0.0097978149 | K10: =LN(H10/H9) -> 0.012318398 | M10: 40788 | N10: 320.3 | O10: 16821.46 | P10: =LN(O10/O9) -> 0.0086399184 | Q10: =LN(N10/N9) -> -0.0018714915
A11: 40834 | B11: 330.55 | C11: 16748.29 | D11: =LN(C11/C10) -> -0.016391975 | E11: =LN(B11/B10) -> -0.0076848114 | G11: 40861 | H11: 398.6 | I11: 17118.74 | J11: =LN(I11/I10) -> -0.0043180849 | K11: =LN(H11/H10) -> 0.0061654804 | M11: 40791 | N11: 319.45 | O11: 16713.33 | P11: =LN(O11/O10) -> -0.0064488476 | Q11: =LN(N11/N10) -> -0.0026572896
A12: 40835 | B12: 331.55 | C12: 17085.34 | D12: =LN(C12/C11) -> 0.019924622 | E12: =LN(B12/B11) -> 0.003020694 | G12: 40862 | H12: 391.7 | I12: 16882.67 | J12: =LN(I12/I11) -> -0.013886118 | K12: =LN(H12/H11) -> -0.017462167 | M12: 40792 | N12: 319.9 | O12: 16862.81 | P12: =LN(O12/O11) -> 0.0089040007 | Q12: =LN(N12/N11) -> 0.0014076799
A13: 40836 | B13: 331.35 | C13: 16936.89 | D13: =LN(C13/C12) -> -0.0087267026 | E13: =LN(B13/B12) -> -0.00060340928 | G13: 40863 | H13: 392.05 | I13: 16775.87 | J13: =LN(I13/I12) -> -0.0063461076 | K13: =LN(H13/H12) -> 0.00089314201 | M13: 40793 | N13: 320.35 | O13: 17065 | P13: =LN(O13/O12) -> 0.011918977 | Q13: =LN(N13/N12) -> 0.0014057011
A14: 40837 | B14: 326.1 | C14: 16785.64 | D14: =LN(C14/C13) -> -0.0089703242 | E14: =LN(B14/B13) -> -0.015971136 | G14: 40864 | H14: 389.6 | I14: 16461.71 | J14: =LN(I14/I13) -> -0.018904466 | K14: =LN(H14/H13) -> -0.0062688109 | M14: 40794 | N14: 325.05 | O14: 17165.54 | P14: =LN(O14/O13) -> 0.0058743034 | Q14: =LN(N14/N13) -> 0.014564869
A15: 40840 | B15: 336.35 | C15: 16939.28 | D15: =LN(C15/C14) -> 0.0091114264 | E15: =LN(B15/B14) -> 0.030948202 | G15: 40865 | H15: 390.85 | I15: 16371.51 | J15: =LN(I15/I14) -> -0.005494449 | K15: =LN(H15/H14) -> 0.0032032829 | M15: 40795 | N15: 333.25 | O15: 16866.97 | P15: =LN(O15/O14) -> -0.017546614 | Q15: =LN(N15/N14) -> 0.024913942
A16: 40841 | B16: 340.4 | C16: 17254.86 | D16: =LN(C16/C15) -> 0.018458658 | E16: =LN(B16/B15) -> 0.011969112 | G16: 40868 | H16: 390.15 | I16: 15946.1 | J16: =LN(I16/I15) -> -0.026328344 | K16: =LN(H16/H15) -> -0.0017925741 | M16: 40798 | N16: 345.9 | O16: 16501.74 | P16: =LN(O16/O15) -> -0.021891442 | Q16: =LN(N16/N15) -> 0.037256757
A17: 40842 | B17: 342.85 | C17: 17288.83 | D17: =LN(C17/C16) -> 0.0019667853 | E17: =LN(B17/B16) -> 0.007171637 | G17: 40869 | H17: 384.95 | I17: 16065.42 | J17: =LN(I17/I16) -> 0.0074548508 | K17: =LN(H17/H16) -> -0.013417825 | M17: 40799 | N17: 341.2 | O17: 16467.44 | P17: =LN(O17/O16) -> -0.0020807319 | Q17: =LN(N17/N16) -> -0.0136809
A18: 40844 | B18: 349.45 | C18: 17804.8 | D18: =LN(C18/C17) -> 0.029407456 | E18: =LN(B18/B17) -> 0.019067456 | G18: 40870 | H18: 383 | I18: 15699.97 | J18: =LN(I18/I17) -> -0.023010334 | K18: =LN(H18/H17) -> -0.0050784665 | M18: 40800 | N18: 352.6 | O18: 16709.6 | P18: =LN(O18/O17) -> 0.014598307 | Q18: =LN(N18/N17) -> 0.032865454
A19: 40847 | B19: 375.25 | C19: 17705.01 | D19: =LN(C19/C18) -> -0.0056204335 | E19: =LN(B19/B18) -> 0.071231981 | G19: 40871 | H19: 384.85 | I19: 15858.49 | J19: =LN(I19/I18) -> 0.010046202 | K19: =LN(H19/H18) -> 0.0048186588 | M19: 40801 | N19: 349.3 | O19: 16876.54 | P19: =LN(O19/O18) -> 0.0099410873 | Q19: =LN(N19/N18) -> -0.0094031182
A20: 40848 | B20: 388.45 | C20: 17480.83 | D20: =LN(C20/C19) -> -0.012742798 | E20: =LN(B20/B19) -> 0.034571991 | G20: 40872 | H20: 375.2 | I20: 15695.43 | J20: =LN(I20/I19) -> -0.010335416 | K20: =LN(H20/H19) -> -0.025394431 | M20: 40802 | N20: 340.05 | O20: 16933.83 | P20: =LN(O20/O19) -> 0.0033889043 | Q20: =LN(N20/N19) -> -0.026838486
A21: 40849 | B21: 390.2 | C21: 17464.85 | D21: =LN(C21/C20) -> -0.00091456232 | E21: =LN(B21/B20) -> 0.0044949668 | G21: 40875 | H21: 382.55 | I21: 16167.13 | J21: =LN(I21/I20) -> 0.029610581 | K21: =LN(H21/H20) -> 0.019400147 | M21: 40805 | N21: 338.4 | O21: 16745.35 | P21: =LN(O21/O20) -> -0.011192788 | Q21: =LN(N21/N20) -> -0.0048640379
... A23: 40851 | B23: 378.85 | C23: 17562.61 | D23: =LN(C23/C22) -> 0.0046044344 | E23: =LN(B23/B22) -> -0.0085420061 | G23: 40877 | H23: 396.1 | I23: 16123.46 | J23: =LN(I23/I22) -> 0.0071655178 | K23: =LN(H23/H22) -> 0.022338028 | M23: 40807 | N23: 339.3 | O23: 17065.15 | P23: =LN(O23/O22) -> -0.0019979851 | Q23: =LN(N23/N22) -> -0.01244799
M24: 40808 | N24: 331.8 | O24: 16361.15 | P24: =LN(O24/O23) -> -0.04212875 | Q24: =LN(N24/N23) -> -0.022352294
A25: Average Return | B25: =AVERAGE(E9:E23) -> 0.0094074443 | G25: Average Return | H25: =AVERAGE(K9:K23) -> 0.00087086967 | M25: 40809 | N25: 331 | O25: 16162.06 | P25: =LN(O25/O24) -> -0.012243102 | Q25: =LN(N25/N24) -> -0.0024140024
A26: Alpha | B26: =INTERCEPT(E9:E23,D9:D23) -> 0.0092026555 | G26: Alpha | H26: =INTERCEPT(K9:K23,J9:J23) -> 0.0031688082 | M26: 40812 | N26: 328.45 | O26: 16051.1 | P26: =LN(O26/O25) -> -0.0068891372 | Q26: =LN(N26/N25) -> -0.007733756
A27: Beta | B27: =SLOPE(E9:E23,D9:D23) -> 0.1034789 | G27: Beta | H27: =SLOPE(K9:K23,J9:J23) -> 0.43466105 | M27: 40813 | N27: 338.8 | O27: 16524.03 | P27: =LN(O27/O26) -> 0.029038302 | Q27: =LN(N27/N26) -> 0.031025343
M28: 40814 | N28: 334.4 | O28: 16446.02 | P28: =LN(O28/O27) -> -0.0047321824 | Q28: =LN(N28/N27) -> -0.013072082
M29: 40815 | N29: 343.65 | O29: 16698.07 | P29: =LN(O29/O28) -> 0.015209641 | Q29: =LN(N29/N28) -> 0.027285816
M30: 40816 | N30: 340.25 | O30: 16453.76 | P30: =LN(O30/O29) -> -0.014739121 | Q30: =LN(N30/N29) -> -0.009943056
M31: 40819 | N31: 334.45 | O31: 16151.45 | P31: =LN(O31/O30) -> -0.018544194 | Q31: =LN(N31/N30) -> -0.01719325
M32: 40820 | N32: 327.05 | O32: 15864.86 | P32: =LN(O32/O31) -> -0.017903228 | Q32: =LN(N32/N31) -> -0.022374327
M33: 40821 | N33: 322.05 | O33: 15792.41 | P33: =LN(O33/O32) -> -0.0045771557 | Q33: =LN(N33/N32) -> -0.015406251
M34: 40823 | N34: 329.2 | O34: 16232.54 | P34: =LN(O34/O33) -> 0.027488425 | Q34: =LN(N34/N33) -> 0.021958656
M35: 40826 | N35: 332.4 | O35: 16557.23 | P35: =LN(O35/O34) -> 0.019804995 | Q35: =LN(N35/N34) -> 0.0096735942
M36: 40827 | N36: 326.55 | O36: 16536.47 | P36: =LN(O36/O35) -> -0.0012546196 | Q36: =LN(N36/N35) -> -0.017755987
M37: 40828 | N37: 329.65 | O37: 16958.39 | P37: =LN(O37/O36) -> 0.025194452 | Q37: =LN(N37/N36) -> 0.0094484092
M38: 40829 | N38: 326.75 | O38: 16883.92 | P38: =LN(O38/O37) -> -0.0044010069 | Q38: =LN(N38/N37) -> -0.0088361331
M40: Average Return | N40: =AVERAGE(Q9:Q38) -> 0.00062295877
M41: Alpha | N41: =INTERCEPT(Q9:Q38,P9:P38) -> 0.00040488543
M42: Beta | N42: =SLOPE(Q9:Q38,P9:P38) -> 0.5122345

Sheet Fundamental Beta
A4: Debt to capital | B4: Debt to equity | C4: levered beta
A5: 0 | B5: 0 | C5: =$B$15*(1+(B5*(1-B17))) -> 0.53595125
A6: 0.1 | B6: =A6/90% -> 0.11111111 | C6: =$B$15*(1+(B6*(1-B18))) -> 0.59550139
A7: 0.25 | B7: =A7/75% -> 0.33333333 | C7: =$B$15*(1+(B7*(1-B19))) -> 0.71460167
A8: 0.35 | B8: =A8/65% -> 0.53846154 | C8: =$B$15*(1+(B8*(1-B20))) -> 0.82454039
A9: 0.5 | B9: =A9/50% -> 1 | C9: =$B$15*(1+(B9*(1-B21))) -> 1.0719025
A10: 0.75 | B10: =A10/25% -> 3 | C10: =$B$15*(1+(B10*(1-B21))) -> 2.143805
A13: Years | B13: 2016 | C13: 2017 | D13: 2018 | E13: 2019 | F13: 2020 | G13: 2021 | H13: 2022 | I13: 2023 | J13: 2024 | K13: 2025
A14: DEBT to Equity | B14: ='HUL ASSUMPTION '!B12/('HUL ASSUMPTION '!B9+'HUL ASSUMPTION '!B8) -> 0 | C14: ='HUL ASSUMPTION '!C12/('HUL ASSUMPTION '!C9+'HUL ASSUMPTION '!C8) -> 0 | D14: ='HUL ASSUMPTION '!D12/('HUL ASSUMPTION '!D9+'HUL ASSUMPTION '!D8) -> 0 | E14: ='HUL ASSUMPTION '!E12/('HUL ASSUMPTION '!E9+'HUL ASSUMPTION '!E8) -> 0 | F14: ='HUL ASSUMPTION '!F12/('HUL ASSUMPTION '!F9+'HUL ASSUMPTION '!F8) -> 0 | G14: ='HUL ASSUMPTION '!G12/('HUL ASSUMPTION '!G9+'HUL ASSUMPTION '!G8) -> 0.019880255 | H14: ='HUL ASSUMPTION '!H12/('HUL ASSUMPTION '!H9+'HUL ASSUMPTION '!H8) -> 0.019913864 | I14: ='HUL ASSUMPTION '!I12/('HUL ASSUMPTION '!I9+'HUL ASSUMPTION '!I8) -> 0.020688557 | ... K14: ='HUL ASSUMPTION '!K12/('HUL ASSUMPTION '!K9+'HUL ASSUMPTION '!K8) -> 0.031269709
A15: Unlevered Beta | B15: =Beta!F3 -> 0.53595125
A16: Levered Beta | B16: =$B$15*(1+B14*(1-B17)) -> 0.53595125 | C16: =$B$15*(1+C14*(1-C17)) -> 0.53595125 | D16: =$B$15*(1+D14*(1-D17)) -> 0.53595125 | E16: =$B$15*(1+E14*(1-E17)) -> 0.53595125 | F16: =$B$15*(1+F14*(1-F17)) -> 0.53595125 | G16: =$B$15*(1+G14*(1-G17)) -> 0.54410947 | H16: =$B$15*(1+H14*(1-H17)) -> 0.54409841 | I16: =$B$15*(1+I14*(1-I17)) -> 0.54456211 | ... K16: =$B$15*(1+K14*(1-K17)) -> 0.54857913
A17: Tax rate | B17: ='HUL ASSUMPTION '!B106 -> 0.30541541 | C17: ='HUL ASSUMPTION '!C106 -> 0.29158849 | D17: ='HUL ASSUMPTION '!D106 -> 0.29485244 | E17: ='HUL ASSUMPTION '!E106 -> 0.30098568 | F17: ='HUL ASSUMPTION '!F106 -> 0.24219094 | G17: ='HUL ASSUMPTION '!G106 -> 0.2343184 | H17: ='HUL ASSUMPTION '!H106 -> 0.23664707 | I17: ='HUL ASSUMPTION '!I106 -> 0.22341158 | ... K17: ='HUL ASSUMPTION '!K106 -> 0.2465035

Sheet Accounting Beta
A4: year | B4: HUL | C4: ITC | D4: DABUR LTD | E4: AVERAGE | F4: BETA
A5: 2016 | B5: 82.71 | C5: 25.79 | D5: 34.52 | E5: =AVERAGE(B5:D5) -> 47.673333 | F5: =SLOPE(B5:B14,E5:E14) -> 2.7959609
A6: 2017 | B6: 70.33 | C6: 23.45 | D6: 29.57 | E6: =AVERAGE(B6:D6) -> 41.116667
A7: 2018 | B7: 77.21 | C7: 23.2 | D7: 27.19 | E7: =AVERAGE(B7:D7) -> 42.533333
A8: 2019 | B8: 81.93 | C8: 22.8 | D8: 30.85 | E8: =AVERAGE(B8:D8) -> 45.193333
A9: 2020 | B9: 85.89 | C9: 24.82 | D9: 27.4 | E9: =AVERAGE(B9:D9) -> 46.036667
A10: 2021 | B10: 28.68 | C10: 21.18 | D10: 27.73 | E10: =AVERAGE(B10:D10) -> 25.863333
A11: 2022 | B11: 18.33 | C11: 25.01 | D11: 25.46 | E11: =AVERAGE(B11:D11) -> 22.933333
A12: 2023 | B12: 20.13 | C12: 29.08 | D12: 22.6 | E12: =AVERAGE(B12:D12) -> 23.936667
A13: 2024 | B13: 19.99 | C13: 29.21 | D13: 22.86 | E13: =AVERAGE(B13:D13) -> 24.02
A14: 2025 | B14: 21.26 | C14: 27.91 | D14: 19.57 | E14: =AVERAGE(B14:D14) -> 22.913333

Sheet WACC
A1: weighted average cost of capital | B1: Column2 | C1: Column3
A2: INPUT | C2: VALUE
A3: Risk Free Premium | B3: Rf | C3: 0.0668
A4: Beta | B4: B | C4: =Beta!F3 -> 0.53595125
A5: Market Return | B5: MR | C5: 0.12
A6: Cost of Equity | B6: Ke | C6: =C3+C4*(C5-C3) -> 0.095312607
A7: Interest Expense | C7: ='HUL ASSUMPTION '!K80 -> 364
A8: Total Debt | C8: ='HUL ASSUMPTION '!K12 -> 1537
A9: Cost of Debt | B9: Kd | C9: =C7/C8 -> 0.23682498
A10: Tax Rate | B10: t | C10: ='HUL ASSUMPTION '!K106 -> 0.2465035
A11: Total Equity | C11: ='HUL ASSUMPTION '!K8+'HUL ASSUMPTION '!K9 -> 49153
A12: Weight of Equity | C12: =C11/(C11+C8) -> 0.96967844
A13: Weight of Debt | C13: =C8/(C8+C11) -> 0.030321562
A14: WACC | C14: =C12*C6+C13*C9*(1-C10) -> 0.097833365

Sheet EVA
A1: EVA
A2: INPUT | C2: VALUE
A3: WACC | C3: =WACC!C14 -> 0.097833365
A4: TOTAL CAPITAL EMPLOYED | C4: =WACC!C8+WACC!C11 -> 50690
A5: EBIT | C5: ='HUL ASSUMPTION '!K85+'HUL ASSUMPTION '!K80 -> 14664
A6: TAX | C6: ='HUL ASSUMPTION '!K106 -> 0.2465035
A7: NOPAT | C7: =C5*(1-C6) -> 11049.273
A8: EVA | C8: =C7-(C3*C4) -> 6090.0994

Sheet DCF
A1: Discounted Cash Flow
B2: 2026 | C2: 2027 | D2: 2028 | E2: 2029 | F2: 2030
A3: EBIT | B3: ='HUL ASSUMPTION '!L85+'HUL ASSUMPTION '!L80 -> 16372.138 | C3: ='HUL ASSUMPTION '!M85+'HUL ASSUMPTION '!M80 -> 18379.55 | D3: ='HUL ASSUMPTION '!N85+'HUL ASSUMPTION '!N80 -> 20795.136 | E3: ='HUL ASSUMPTION '!O85+'HUL ASSUMPTION '!O80 -> 23788.553 | F3: ='HUL ASSUMPTION '!P85+'HUL ASSUMPTION '!P80 -> 27627.928
A4: NOPAT | B4: =B3*(1-0.25) -> 12279.103 | C4: =C3*(1-0.25) -> 13784.663 | D4: =D3*(1-0.25) -> 15596.352 | E4: =E3*(1-0.25) -> 17841.415 | F4: =F3*(1-0.25) -> 20720.946
A5: DEP | B5: ='HUL ASSUMPTION '!L83 -> 1442.2066 | C5: ='HUL ASSUMPTION '!M83 -> 1699.3136 | D5: ='HUL ASSUMPTION '!N83 -> 2002.2559 | E5: ='HUL ASSUMPTION '!O83 -> 2359.2048 | F5: ='HUL ASSUMPTION '!P83 -> 2779.7882
A6: Capex | B6: ='HUL ASSUMPTION '!L50 -> 1210.6524 | C6: ='HUL ASSUMPTION '!M50 -> 1235.5831 | D6: ='HUL ASSUMPTION '!N50 -> 1261.0273 | E6: ='HUL ASSUMPTION '!O50 -> 1286.9954 | F6: ='HUL ASSUMPTION '!P50 -> 1313.4983
A7: CHANGE IN W.C | B7: =Table4[[#Totals],[Balance sheet102]] -> 713.227 | C7: =Table4[[#Totals],[Balance sheet103]] -> 814.50805 | D7: =Table4[[#Totals],[Balance sheet104]] -> 929.37956 | E7: =Table4[[#Totals],[Balance sheet105]] -> 1059.6006 | F7: =Table4[[#Totals],[Balance sheet106]] -> 1207.1523
A8: FCFF | B8: =B4+B5-B6-B7 -> 11797.431 | C8: =C4+C5-C6-C7 -> 13433.885 | D8: =D4+D5-D6-D7 -> 15408.201 | E8: =E4+E5-E6-E7 -> 17854.024 | F8: =F4+F5-F6-F7 -> 20980.083
A9: WACC | B9: =WACC!C14 -> 0.097833365
A10: DISCOUNT FCFF | B10: =B8/(1+$B$9)^1 -> 10746.103 | C10: =C8/(1+$B$9)^2 -> 11146.25 | D10: =D8/(1+$B$9)^3 -> 11645.085 | E10: =E8/(1+$B$9)^4 -> 12291.09 | F10: =F8/(1+$B$9)^5 -> 13156.037 | G10: =SUM(B10:F10) -> 58984.565
A11: TERMINAL VALUE | B11: =(F8*(1+0.035))/(B9-0.035) -> 345586.87
A12: TERMINAL VALUE DISCOUNT | B12: =B11/((1+B9)^5) -> 216708.08
A13: ENTERPRISE VALUE | B13: =B12+G10 -> 275692.65
A14: EQUITY VALUE | B14: =B13+'HUL ASSUMPTION '!K28-'HUL ASSUMPTION '!K12 -> 281448.65
A15: SHARE OUTSTANDING | B15: 258.5 | C15: Hindustan Unilever Ltd. (HINDUNILVR) Shares Outstanding - Investing.com IN
A16: INTERNSIC VALUE | B16: =B14/B15 -> 1088.7762

Sheet DDM
A1: Dividend Discount Model for HUL (Gordon Growth Model)
A7: Intrinsic Value = PV of Stage 1 Dividends + PV of Terminal Value | All amounts in ₹ per share
A9: SECTION 1: KEY ASSUMPTIONS
A10: Parameter | B10: Basis / Source | C10: Value
A11: Last Actual DPS (FY2025, ₹) | B11: HUL ASSUMPTION Sheet – Row 98 | D11: ='HUL ASSUMPTION '!K99 -> 53
A12: Last Actual EPS (FY2025, ₹) | B12: HUL ASSUMPTION Sheet – Row 100 | D12: ='HUL ASSUMPTION '!K101 -> 44.55
A13: Payout Ratio (FY2025) | B13: DPS ÷ EPS | D13: =D11/D12 -> 1.1896745
A14: Stage 1 Growth Rate (g1) | B14: Avg DPS CAGR (recent 3yr, capped) | D14: 0.12
A15: Stage 1 Period (years) | B15: FY2026 – FY2030 | D15: 5
A16: Terminal Growth Rate (g2) | B16: Stable long-run FMCG growth | D16: 0.05
A17: Cost of Equity (Ke) | B17: WACC Sheet – CAPM formula | D17: =WACC!C6 -> 0.095312607
A19: SECTION 2: STAGE 1 — HIGH-GROWTH PHASE (FY2026 – FY2030)
A20: Particulars | B20: FY2026 | C20: FY2027 | D20: FY2028 | E20: FY2029 | F20: FY2030
A21: Forecasted DPS (₹) | B21: =D11*(1+D14)^1 -> 59.36 | C21: =D11*(1+D14)^2 -> 66.4832 | D21: =D11*(1+D14)^3 -> 74.461184 | E21: =D11*(1+D14)^4 -> 83.396526 | F21: =D11*(1+D14)^5 -> 93.404109
A22: Discount Period (n) | B22: 1 | C22: 2 | D22: 3 | E22: 4 | F22: 5
A23: Discount Factor [1/(1+Ke)^n] | B23: =1/(1+D17)^1 -> 0.91298137 | C23: =1/(1+D17)^2 -> 0.83353497 | D23: =1/(1+D17)^3 -> 0.7610019 | E23: =1/(1+D17)^4 -> 0.69478055 | F23: =1/(1+D17)^5 -> 0.6343217
A24: PV of Dividend (₹) | B24: =B21*B23 -> 54.194574 | C24: =C21*C23 -> 55.416072 | D24: =D21*D23 -> 56.665103 | E24: =E21*E23 -> 57.942285 | F24: =F21*F23 -> 59.248253
A25: Sum of PV of Stage 1 Dividends (₹) | F25: =SUM(B24:F24) -> 283.46629
A27: SECTION 3: STAGE 2 — TERMINAL VALUE (Stable Perpetual Growth at g2)
A28: DPS at End of Stage 1 (FY2030, ₹) | F28: =F21 -> 93.404109
A29: Terminal DPS (FY2031 = DPS₂₀₃₀ × (1+g2), ₹) | F29: =D28*(1+D16) -> 0
A30: Terminal Value (= Terminal DPS / (Ke – g2), ₹) | F30: =D29/(D17-D16) -> 0
A31: PV of Terminal Value (₹) | F31: =D30/(1+D17)^D15 -> 0
A33: INTRINSIC VALUE PER SHARE (₹) = PV Stage 1 + PV Terminal Value | F33: =F25+D31 -> 283.46629

Sheet RATIO
A1: RATIO | B1: 2016 | C1: 2017 | D1: 2018 | E1: 2019 | F1: 2020 | G1: 2021 | H1: 2022 | I1: 2023 | J1: 2024 | K1: 2025 | L1: Trend | M1: interpretation
A2: Liquidity Ratios
A3: Current Ratio | B3: ='HUL ASSUMPTION '!B30/'HUL ASSUMPTION '!B35 -> 1.0659952 | C3: ='HUL ASSUMPTION '!C30/'HUL ASSUMPTION '!C35 -> 0.81171897 | D3: ='HUL ASSUMPTION '!D30/'HUL ASSUMPTION '!D35 -> 0.95924039 | E3: ='HUL ASSUMPTION '!E30/'HUL ASSUMPTION '!E35 -> 1.0392673 | F3: ='HUL ASSUMPTION '!F30/'HUL ASSUMPTION '!F35 -> 1.1709139 | G3: ='HUL ASSUMPTION '!G30/'HUL ASSUMPTION '!G35 -> 1.035927 | H3: ='HUL ASSUMPTION '!H30/'HUL ASSUMPTION '!H35 -> 1.0448447 | I3: ='HUL ASSUMPTION '!I30/'HUL ASSUMPTION '!I35 -> 1.1679901 | ... K3: ='HUL ASSUMPTION '!K30/'HUL ASSUMPTION '!K35 -> 1.1303296 | M3: Indicates adequate short-term liquidity. The company comfortably meets short-term obligations without holding excessive idle assets.
A4: Quick Ratio | B4: =('HUL ASSUMPTION '!B30-'HUL ASSUMPTION '!B25)/'HUL ASSUMPTION '!B35 -> 0.68595911 | C4: =('HUL ASSUMPTION '!C30-'HUL ASSUMPTION '!C25)/'HUL ASSUMPTION '!C35 -> 0.48375451 | D4: =('HUL ASSUMPTION '!D30-'HUL ASSUMPTION '!D25)/'HUL ASSUMPTION '!D35 -> 0.68608152 | E4: =('HUL ASSUMPTION '!E30-'HUL ASSUMPTION '!E25)/'HUL ASSUMPTION '!E35 -> 0.74931162 | F4: =('HUL ASSUMPTION '!F30-'HUL ASSUMPTION '!F25)/'HUL ASSUMPTION '!F35 -> 0.88137083 | G4: =('HUL ASSUMPTION '!G30-'HUL ASSUMPTION '!G25)/'HUL ASSUMPTION '!G35 -> 0.71608206 | H4: =('HUL ASSUMPTION '!H30-'HUL ASSUMPTION '!H25)/'HUL ASSUMPTION '!H35 -> 0.67989492 | I4: =('HUL ASSUMPTION '!I30-'HUL ASSUMPTION '!I25)/'HUL ASSUMPTION '!I35 -> 0.81233457 | ... K4: =('HUL ASSUMPTION '!K30-'HUL ASSUMPTION '!K25)/'HUL ASSUMPTION '!K35 -> 0.85822652 | M4: Shows sufficient liquidity even after excluding inventory. Acceptable for FMCG companies with fast-moving inventory cycles.
A5: Profitability Ratios
A6: Gross Margin | B6: ='HUL ASSUMPTION '!B82/'HUL ASSUMPTION '!B63 -> 0.20176427 | C6: ='HUL ASSUMPTION '!C82/'HUL ASSUMPTION '!C63 -> 0.21298213 | D6: ='HUL ASSUMPTION '!D82/'HUL ASSUMPTION '!D63 -> 0.22485156 | E6: ='HUL ASSUMPTION '!E82/'HUL ASSUMPTION '!E63 -> 0.2366576 | F6: ='HUL ASSUMPTION '!F82/'HUL ASSUMPTION '!F63 -> 0.25860513 | G6: ='HUL ASSUMPTION '!G82/'HUL ASSUMPTION '!G63 -> 0.25006522 | H6: ='HUL ASSUMPTION '!H82/'HUL ASSUMPTION '!H63 -> 0.24933096 | I6: ='HUL ASSUMPTION '!I82/'HUL ASSUMPTION '!I63 -> 0.23855336 | ... K6: ='HUL ASSUMPTION '!K82/'HUL ASSUMPTION '!K63 -> 0.25255007 | M6: Indicates strong pricing power and brand strength. Stable gross margins reflect efficient cost management and premium product positioning.
A7: Operating Margin | B7: ='HUL ASSUMPTION '!B78/'HUL ASSUMPTION '!B63 -> 0.20224719 | C7: ='HUL ASSUMPTION '!C78/'HUL ASSUMPTION '!C63 -> 0.213672 | D7: ='HUL ASSUMPTION '!D78/'HUL ASSUMPTION '!D63 -> 0.22543085 | E7: ='HUL ASSUMPTION '!E78/'HUL ASSUMPTION '!E63 -> 0.23739012 | F7: ='HUL ASSUMPTION '!F78/'HUL ASSUMPTION '!F63 -> 0.26133815 | G7: ='HUL ASSUMPTION '!G78/'HUL ASSUMPTION '!G63 -> 0.25241325 | H7: ='HUL ASSUMPTION '!H78/'HUL ASSUMPTION '!H63 -> 0.25124529 | I7: ='HUL ASSUMPTION '!I78/'HUL ASSUMPTION '!I63 -> 0.24026106 | ... K7: ='HUL ASSUMPTION '!K78/'HUL ASSUMPTION '!K63 -> 0.25847175 | M7: Demonstrates operational efficiency. HUL maintains strong control over operating expenses, consistent with FMCG industry leaders.
A8: Net Margin | B8: ='HUL ASSUMPTION '!B89/'HUL ASSUMPTION '!B63 -> 0.13318953 | C8: ='HUL ASSUMPTION '!C89/'HUL ASSUMPTION '!C63 -> 0.14079649 | D8: ='HUL ASSUMPTION '!D89/'HUL ASSUMPTION '!D63 -> 0.15168718 | E8: ='HUL ASSUMPTION '!E89/'HUL ASSUMPTION '!E63 -> 0.15791126 | F8: ='HUL ASSUMPTION '!F89/'HUL ASSUMPTION '!F63 -> 0.17372696 | G8: ='HUL ASSUMPTION '!G89/'HUL ASSUMPTION '!G63 -> 0.17292808 | H8: ='HUL ASSUMPTION '!H89/'HUL ASSUMPTION '!H63 -> 0.17225011 | I8: ='HUL ASSUMPTION '!I89/'HUL ASSUMPTION '!I63 -> 0.16843636 | ... K8: ='HUL ASSUMPTION '!K89/'HUL ASSUMPTION '!K63 -> 0.17316045 | M8: Reflects stable bottom-line profitability. Shows the company’s ability to convert revenue into net earnings efficiently.
A9: ROE | B9: ='HUL ASSUMPTION '!B89/('HUL ASSUMPTION '!B8+'HUL ASSUMPTION '!B9) -> 0.65886288 | C9: ='HUL ASSUMPTION '!C89/('HUL ASSUMPTION '!C8+'HUL ASSUMPTION '!C9) -> 0.69183359 | D9: ='HUL ASSUMPTION '!D89/('HUL ASSUMPTION '!D8+'HUL ASSUMPTION '!D9) -> 0.74021201 | E9: ='HUL ASSUMPTION '!E89/('HUL ASSUMPTION '!E8+'HUL ASSUMPTION '!E9) -> 0.78809244 | F9: ='HUL ASSUMPTION '!F89/('HUL ASSUMPTION '!F8+'HUL ASSUMPTION '!F9) -> 0.83899888 | G9: ='HUL ASSUMPTION '!G89/('HUL ASSUMPTION '!G8+'HUL ASSUMPTION '!G9) -> 0.16768563 | H9: ='HUL ASSUMPTION '!H89/('HUL ASSUMPTION '!H8+'HUL ASSUMPTION '!H9) -> 0.18084495 | I9: ='HUL ASSUMPTION '!I89/('HUL ASSUMPTION '!I8+'HUL ASSUMPTION '!I9) -> 0.19836323 | ... K9: ='HUL ASSUMPTION '!K89/('HUL ASSUMPTION '!K8+'HUL ASSUMPTION '!K9) -> 0.21654833 | M9: Indicates strong returns to shareholders. The normalization post-2021 reflects expansion in equity base due to structural changes.
A10: ROA | B10: ='HUL ASSUMPTION '!B89/'HUL ASSUMPTION '!B42 -> 0.56920748 | C10: ='HUL ASSUMPTION '!C89/'HUL ASSUMPTION '!C42 -> 0.59478077 | D10: ='HUL ASSUMPTION '!D89/'HUL ASSUMPTION '!D42 -> 0.61517679 | E10: ='HUL ASSUMPTION '!E89/'HUL ASSUMPTION '!E42 -> 0.63456686 | F10: ='HUL ASSUMPTION '!F89/'HUL ASSUMPTION '!F42 -> 0.64183654 | G10: ='HUL ASSUMPTION '!G89/'HUL ASSUMPTION '!G42 -> 0.15428782 | H10: ='HUL ASSUMPTION '!H89/'HUL ASSUMPTION '!H42 -> 0.16657536 | I10: ='HUL ASSUMPTION '!I89/'HUL ASSUMPTION '!I42 -> 0.18391611 | ... K10: ='HUL ASSUMPTION '!K89/'HUL ASSUMPTION '!K42 -> 0.18859634 | M10: Shows efficient utilization of total assets in generating profits. Remains strong for a large FMCG firm.
A11: ROCE | B11: ='HUL ASSUMPTION '!B78/('HUL ASSUMPTION '!B42-'HUL ASSUMPTION '!B33) -> 6.9337748 | C11: ='HUL ASSUMPTION '!C78/('HUL ASSUMPTION '!C42-'HUL ASSUMPTION '!C33) -> 9.2833787 | D11: ='HUL ASSUMPTION '!D78/('HUL ASSUMPTION '!D42-'HUL ASSUMPTION '!D33) -> 14.74053 | E11: ='HUL ASSUMPTION '!E78/('HUL ASSUMPTION '!E42-'HUL ASSUMPTION '!E33) -> 5.4662651 | F11: ='HUL ASSUMPTION '!F78/('HUL ASSUMPTION '!F42-'HUL ASSUMPTION '!F33) -> 5.593819 | G11: ='HUL ASSUMPTION '!G78/('HUL ASSUMPTION '!G42-'HUL ASSUMPTION '!G33) -> 0.27998167 | H11: ='HUL ASSUMPTION '!H78/('HUL ASSUMPTION '!H42-'HUL ASSUMPTION '!H33) -> 0.30183986 | I11: ='HUL ASSUMPTION '!I78/('HUL ASSUMPTION '!I42-'HUL ASSUMPTION '!I33) -> 0.32885145 | ... K11: ='HUL ASSUMPTION '!K78/('HUL ASSUMPTION '!K42-'HUL ASSUMPTION '!K33) -> 0.36361972 | M11: Reflects excellent capital efficiency. A ROCE above 25% is considered strong in FMCG, indicating effective capital deployment.
A12: Leverage Ratios
A13: Debt-Equity | B13: ='HUL ASSUMPTION '!B12/('HUL ASSUMPTION '!B8+'HUL ASSUMPTION '!B9) -> 0 | C13: ='HUL ASSUMPTION '!C12/('HUL ASSUMPTION '!C8+'HUL ASSUMPTION '!C9) -> 0 | D13: ='HUL ASSUMPTION '!D12/('HUL ASSUMPTION '!D8+'HUL ASSUMPTION '!D9) -> 0 | E13: ='HUL ASSUMPTION '!E12/('HUL ASSUMPTION '!E8+'HUL ASSUMPTION '!E9) -> 0 | F13: ='HUL ASSUMPTION '!F12/('HUL ASSUMPTION '!F8+'HUL ASSUMPTION '!F9) -> 0 | G13: ='HUL ASSUMPTION '!G12/('HUL ASSUMPTION '!G8+'HUL ASSUMPTION '!G9) -> 0.019880255 | H13: ='HUL ASSUMPTION '!H12/('HUL ASSUMPTION '!H8+'HUL ASSUMPTION '!H9) -> 0.019913864 | I13: ='HUL ASSUMPTION '!I12/('HUL ASSUMPTION '!I8+'HUL ASSUMPTION '!I9) -> 0.020688557 | ... K13: ='HUL ASSUMPTION '!K12/('HUL ASSUMPTION '!K8+'HUL ASSUMPTION '!K9) -> 0.031269709 | M13: Extremely low leverage. HUL operates primarily through internal accruals, minimizing financial risk.
A14: Interest Coverage | B14: ='HUL ASSUMPTION '!B78/'HUL ASSUMPTION '!B80 -> 418.8 | C14: ='HUL ASSUMPTION '!C78/'HUL ASSUMPTION '!C80 -> 309.72727 | D14: ='HUL ASSUMPTION '!D78/'HUL ASSUMPTION '!D80 -> 389.15 | E14: ='HUL ASSUMPTION '!E78/'HUL ASSUMPTION '!E80 -> 324.07143 | F14: ='HUL ASSUMPTION '!F78/'HUL ASSUMPTION '!F80 -> 95.622642 | G14: ='HUL ASSUMPTION '!G78/'HUL ASSUMPTION '!G80 -> 107.5 | H14: ='HUL ASSUMPTION '!H78/'HUL ASSUMPTION '!H80 -> 131.2449 | I14: ='HUL ASSUMPTION '!I78/'HUL ASSUMPTION '!I80 -> 140.69307 | ... K14: ='HUL ASSUMPTION '!K78/'HUL ASSUMPTION '!K80 -> 43.648352 | M14: Indicates very strong ability to meet interest obligations. Low financial distress risk.
A15: Efficiency Ratios
A16: Inventory Turnover | B16: - | C16: =Table5[[#Totals],[Column3]]/'HUL ASSUMPTION '!C45 -> 6.6229039 | D16: =Table5[[#Totals],[Column4]]/'HUL ASSUMPTION '!D45 -> 7.2340606 | E16: =Table5[[#Totals],[Column5]]/'HUL ASSUMPTION '!E45 -> 7.8297427 | F16: =Table5[[#Totals],[Column6]]/'HUL ASSUMPTION '!F45 -> 7.3155397 | G16: =Table5[[#Totals],[Column7]]/'HUL ASSUMPTION '!G45 -> 7.6208673 | H16: =Table5[[#Totals],[Column8]]/'HUL ASSUMPTION '!H45 -> 7.1508318 | I16: =Table5[[#Totals],[Column9]]/'HUL ASSUMPTION '!I45 -> 8.0979674 | J16: =Table5[[#Totals],[Column10]]/'HUL ASSUMPTION '!J45 -> 7.7202601 | K16: =Table5[[#Totals],[Column11]]/'HUL ASSUMPTION '!K45 -> 7.8281701 | M16: Efficient inventory management. Fast-moving product portfolio and strong distribution network.
A17: Receivable Turnover | B17: - | C17: ='HUL ASSUMPTION '!C63/'HUL ASSUMPTION '!C46 -> 32.018072 | D17: ='HUL ASSUMPTION '!D63/'HUL ASSUMPTION '!D46 -> 33.277108 | E17: ='HUL ASSUMPTION '!E63/'HUL ASSUMPTION '!E46 -> 27.10922 | F17: ='HUL ASSUMPTION '!F63/'HUL ASSUMPTION '!F46 -> 28.528871 | G17: ='HUL ASSUMPTION '!G63/'HUL ASSUMPTION '!G46 -> 34.146993 | H17: ='HUL ASSUMPTION '!H63/'HUL ASSUMPTION '!H46 -> 28.599441 | I17: ='HUL ASSUMPTION '!I63/'HUL ASSUMPTION '!I46 -> 25.345618 | J17: ='HUL ASSUMPTION '!J63/'HUL ASSUMPTION '!J46 -> 22.292719 | K17: ='HUL ASSUMPTION '!K63/'HUL ASSUMPTION '!K46 -> 20.022476 | M17: Strong credit management and quick collection cycle. Low receivable risk.
A18: Payable Turnover | B18: - | C18: =Table5[[#Totals],[Column3]]/'HUL ASSUMPTION '!C47 -> 2.4577673 | D18: =Table5[[#Totals],[Column4]]/'HUL ASSUMPTION '!D47 -> 2.3075676 | E18: =Table5[[#Totals],[Column5]]/'HUL ASSUMPTION '!E47 -> 2.3637052 | F18: =Table5[[#Totals],[Column6]]/'HUL ASSUMPTION '!F47 -> 2.2373927 | G18: =Table5[[#Totals],[Column7]]/'HUL ASSUMPTION '!G47 -> 2.4435329 | H18: =Table5[[#Totals],[Column8]]/'HUL ASSUMPTION '!H47 -> 2.5480378 | I18: =Table5[[#Totals],[Column9]]/'HUL ASSUMPTION '!I47 -> 3.0142857 | J18: =Table5[[#Totals],[Column10]]/'HUL ASSUMPTION '!J47 -> 2.6686941 | K18: =Table5[[#Totals],[Column11]]/'HUL ASSUMPTION '!K47 -> 2.5497998 | M18: Strong credit management and quick collection cycle. Low receivable risk.
A19: Asset Turnover | B19: ='HUL ASSUMPTION '!B63/'HUL ASSUMPTION '!B42 -> 4.2736654 | C19: ='HUL ASSUMPTION '!C63/'HUL ASSUMPTION '!C42 -> 4.2244006 | D19: ='HUL ASSUMPTION '!D63/'HUL ASSUMPTION '!D42 -> 4.0555621 | E19: ='HUL ASSUMPTION '!E63/'HUL ASSUMPTION '!E42 -> 4.0185029 | F19: ='HUL ASSUMPTION '!F63/'HUL ASSUMPTION '!F42 -> 3.6945132 | G19: ='HUL ASSUMPTION '!G63/'HUL ASSUMPTION '!G42 -> 0.89220802 | H19: ='HUL ASSUMPTION '!H63/'HUL ASSUMPTION '!H42 -> 0.96705518 | I19: ='HUL ASSUMPTION '!I63/'HUL ASSUMPTION '!I42 -> 1.0919027 | ... K19: ='HUL ASSUMPTION '!K63/'HUL ASSUMPTION '!K42 -> 1.0891421 | M19: Structured supplier payment cycle. Efficient working capital management.
A20: Dividend Payout | B20: ='HUL ASSUMPTION '!B98/'HUL ASSUMPTION '!B89 -> 0.38675369 | C20: ='HUL ASSUMPTION '!C98/'HUL ASSUMPTION '!C89 -> 0.37861915 | D20: ='HUL ASSUMPTION '!D98/'HUL ASSUMPTION '!D89 -> 0.38189803 | E20: ='HUL ASSUMPTION '!E98/'HUL ASSUMPTION '!E89 -> 0.36447979 | F20: ='HUL ASSUMPTION '!F98/'HUL ASSUMPTION '!F89 -> 0.37102998 | G20: ='HUL ASSUMPTION '!G98/'HUL ASSUMPTION '!G89 -> 0.50917777 | H20: ='HUL ASSUMPTION '!H98/'HUL ASSUMPTION '!H89 -> 0.38557496 | I20: ='HUL ASSUMPTION '!I98/'HUL ASSUMPTION '!I89 -> 0.39148765 | ... K20: ='HUL ASSUMPTION '!K98/'HUL ASSUMPTION '!K89 -> 0.49793311 | M20: Indicates stable asset productivity following balance sheet expansion.
A21: Market Ratio
A22: EPS | B22: ='HUL ASSUMPTION '!B89/RATIO!B24 -> 41.37 | C22: ='HUL ASSUMPTION '!C89/RATIO!C24 -> 44.9 | D22: ='HUL ASSUMPTION '!D89/RATIO!D24 -> 52.37 | E22: ='HUL ASSUMPTION '!E89/RATIO!E24 -> 60.36 | F22: ='HUL ASSUMPTION '!F89/RATIO!F24 -> 67.38 | G22: ='HUL ASSUMPTION '!G89/RATIO!G24 -> 79.54 | H22: ='HUL ASSUMPTION '!H89/RATIO!H24 -> 88.18 | I22: ='HUL ASSUMPTION '!I89/RATIO!I24 -> 99.62 | ... K22: ='HUL ASSUMPTION '!K89/RATIO!K24 -> 106.44 | M22: Reflects sustainable earnings growth and increasing shareholder value.
A23: BVPS | B23: =('HUL ASSUMPTION '!B8+'HUL ASSUMPTION '!B9)/RATIO!B24 -> 62.79 | C23: =('HUL ASSUMPTION '!C8+'HUL ASSUMPTION '!C9)/RATIO!C24 -> 64.9 | D23: =('HUL ASSUMPTION '!D8+'HUL ASSUMPTION '!D9)/RATIO!D24 -> 70.75 | E23: =('HUL ASSUMPTION '!E8+'HUL ASSUMPTION '!E9)/RATIO!E24 -> 76.59 | F23: =('HUL ASSUMPTION '!F8+'HUL ASSUMPTION '!F9)/RATIO!F24 -> 80.31 | G23: =('HUL ASSUMPTION '!G8+'HUL ASSUMPTION '!G9)/RATIO!G24 -> 474.34 | H23: =('HUL ASSUMPTION '!H8+'HUL ASSUMPTION '!H9)/RATIO!H24 -> 487.6 | I23: =('HUL ASSUMPTION '!I8+'HUL ASSUMPTION '!I9)/RATIO!I24 -> 502.21 | ... K23: =('HUL ASSUMPTION '!K8+'HUL ASSUMPTION '!K9)/RATIO!K24 -> 491.53 | M23: Indicates strengthening of equity base and net worth.
A24: DPS | B24: ='HUL ASSUMPTION '!B98/'HUL ASSUMPTION '!B99 -> 100 | C24: ='HUL ASSUMPTION '!C98/'HUL ASSUMPTION '!C99 -> 100 | D24: ='HUL ASSUMPTION '!D98/'HUL ASSUMPTION '!D99 -> 100 | E24: ='HUL ASSUMPTION '!E98/'HUL ASSUMPTION '!E99 -> 100 | F24: ='HUL ASSUMPTION '!F98/'HUL ASSUMPTION '!F99 -> 100 | G24: ='HUL ASSUMPTION '!G98/'HUL ASSUMPTION '!G99 -> 100 | H24: ='HUL ASSUMPTION '!H98/'HUL ASSUMPTION '!H99 -> 100 | I24: ='HUL ASSUMPTION '!I98/'HUL ASSUMPTION '!I99 -> 100 | ... K24: ='HUL ASSUMPTION '!K98/'HUL ASSUMPTION '!K99 -> 100

Sheet Ratio Forecast
A1: HINDUSTAN UNILEVER LIMITED — KEY FINANCIAL RATIOS FORECAST (FY2026–FY2030)
A2: Trend-based forecasting anchored to FY2016–FY2025 historical averages | FMCG stable-margin assumptions
A3: # | B3: Ratio / Metric | C3: FY2026E | D3: FY2027E | E3: FY2028E | F3: FY2029E | G3: FY2030E | I3: Interpretation & Investment Insight
A4: LIQUIDITY RATIOS
A5: 1 | B5: Current Ratio | C5: 1.14 | D5: 1.18 | E5: 1.21 | F5: 1.24 | G5: 1.27 | I5: Gradual improvement expected; remains in healthy 1.1–1.3x FMCG comfort band as receivables expand.
A6: 2 | B6: Quick Ratio | C6: 0.87 | D6: 0.9 | E6: 0.93 | F6: 0.96 | G6: 0.99 | I6: Improving as cash generation accelerates; below 1.0x typical & acceptable for fast-moving FMCG cycles.
A7: PROFITABILITY RATIOS
A8: 3 | B8: Gross Margin | C8: 0.255 | D8: 0.26 | E8: 0.264 | F8: 0.268 | G8: 0.271 | I8: Mild expansion as premiumisation drives mix shift and palm oil/crude derivative costs normalize.
A9: 4 | B9: EBITDA Margin | C9: 0.302 | D9: 0.308 | E9: 0.313 | F9: 0.318 | G9: 0.322 | I9: Steady improvement driven by operating leverage; consistent with Unilever global FMCG benchmark of 30%+.
A10: 5 | B10: Operating (EBIT) Margin | C10: 0.281 | D10: 0.286 | E10: 0.29 | F10: 0.294 | G10: 0.298 | I10: Strong EBIT trajectory; incremental D&A from rising capex moderates pace of improvement.
A11: 6 | B11: Net Profit Margin | C11: 0.175 | D11: 0.178 | E11: 0.181 | F11: 0.184 | G11: 0.186 | I11: Stable net margin; effective tax rate ~24.7% holds; rising finance costs partially offset earnings.
A12: 7 | B12: Return on Equity (ROE) | C12: 0.215 | D12: 0.22 | E12: 0.226 | F12: 0.231 | G12: 0.237 | I12: Steadily improving ROE reflects compounding retained earnings; well above FMCG sector median of 18%.
A13: 8 | B13: Return on Assets (ROA) | C13: 0.19 | D13: 0.195 | E13: 0.2 | F13: 0.205 | G13: 0.21 | I13: Efficient asset utilisation; asset-light model supports superior ROA vs global FMCG comps.
A14: 9 | B14: Return on Capital Employed (ROCE) | C14: 0.36 | D14: 0.372 | E14: 0.385 | F14: 0.397 | G14: 0.41 | I14: ROCE sustainably above WACC (9.8%); strong positive EVA creation; capital allocation highly efficient.
A15: LEVERAGE RATIOS
A16: 10 | B16: Debt-to-Equity Ratio | C16: 0.033 | D16: 0.035 | E16: 0.037 | F16: 0.04 | G16: 0.042 | I16: Near debt-free; minor lease obligations keep D/E negligible; no financial distress risk whatsoever.
A17: 11 | B17: Interest Coverage Ratio | C17: 40 | D17: 37.5 | E17: 35.2 | F17: 33 | G17: 30.8 | I17: Declining modestly as finance costs rise on lease obligations; still extremely robust vs 3x minimum threshold.
A18: EFFICIENCY RATIOS
A19: 12 | B19: Inventory Turnover | C19: 7.9 | D19: 8.1 | E19: 8.3 | F19: 8.5 | G19: 8.7 | I19: Improving inventory cycles as supply-chain digitisation and AI-based demand sensing mature.
A20: 13 | B20: Receivables Turnover | C20: 19.5 | D20: 19 | E20: 18.6 | F20: 18.2 | G20: 17.8 | I20: Slight softening as credit extended to modern trade & e-com channels; still best-in-class for FMCG.
A21: 14 | B21: Payables Turnover | C21: 2.55 | D21: 2.6 | E21: 2.65 | F21: 2.68 | G21: 2.7 | I21: Stable; HUL retains strong supplier negotiation leverage given dominant market position and volumes.
A22: 15 | B22: Asset Turnover | C22: 1.1 | D22: 1.12 | E22: 1.15 | F22: 1.17 | G22: 1.2 | I22: Stabilising post-GSKCH integration; modest improvement as revenue scales faster than asset base.
A23: MARKET RATIOS
A24: 16 | B24: EPS (₹ per share) | C24: 49.1 | D24: 54 | E24: 59.5 | F24: 65.5 | G24: 72.2 | I24: Consistent ~10% EPS CAGR; in line with revenue growth and stable margin profile. Strong EPS trajectory.
A25: 17 | B25: BVPS (₹ per share) | C25: 491 | D25: 510 | E25: 530 | F25: 552 | G25: 576 | I25: BVPS growth driven by retained earnings; reflects disciplined reinvestment and compounding equity base.
A26: 18 | B26: P/E Ratio (implied) | C26: 55 | D26: 53.5 | E26: 52 | F26: 50.5 | G26: 49 | I26: Moderate P/E de-rating as EPS accelerates; still commands premium vs FMCG sector median ~45x.
A27: Note: Ratios derived from trend-based forecasting of HUL historical financials (FY2016–FY2025). Margins expressed as % of Net Revenue. EPS & BVPS in ₹/share.

Sheet Peer Valuation
A1: HINDUSTAN UNILEVER LIMITED — RELATIVE VALUATION & PEER COMPARISON
A2: Peer universe: HUL | ITC Ltd | Nestlé India | Dabur India | Britannia Industries | INR Crores
A3: SECTION A — REVENUE TREND (₹ Crores, FY2021–FY2025)
B4: Company | C4: FY2021 | D4: FY2022 | E4: FY2023 | F4: FY2024 | G4: FY2025 | H4: CAGR 3Y
B5: HUL | C5: 45996 | D5: 51193 | E5: 59144 | F5: 60469 | G5: 61469 | H5: 0.062874177
B6: ITC Ltd | C6: 49258 | D6: 59926 | E6: 69481 | F6: 71987 | G6: 78540 | H6: 0.094355779
B7: Nestlé India | C7: 14076 | D7: 15943 | E7: 20669 | F7: 23675 | G7: 26024 | H7: 0.17742884
B8: Dabur India | C8: 10186 | D8: 11530 | E8: 13083 | F8: 12547 | G8: 12562 | H8: 0.028986856
B9: Britannia | C9: 12272 | D9: 14284 | E9: 15777 | F9: 16055 | G9: 17260 | H9: 0.065116183
A11: SECTION B — NET PROFIT TREND (₹ Crores, FY2021–FY2025)
B12: Company | C12: FY2021 | D12: FY2022 | E12: FY2023 | F12: FY2024 | G12: FY2025 | H12: CAGR 3Y
B13: HUL | C13: 10323 | D13: 12386 | E13: 13886 | F13: 13775 | G13: 14452 | H13: 0.052767071
B14: ITC Ltd | C14: 13383 | D14: 16520 | E14: 19194 | F14: 20507 | G14: 22075 | H14: 0.10144688
B15: Nestlé India | C15: 1911 | D15: 2461 | E15: 3390 | F15: 3939 | G15: 4552 | H15: 0.22752463
B16: Dabur India | C16: 1516 | D16: 1664 | E16: 1831 | F16: 1683 | G16: 1657 | H16: -0.0014042145
B17: Britannia | C17: 1249 | D17: 1712 | E17: 1991 | F17: 2234 | G17: 2402 | H17: 0.11949738
A19: SECTION C — KEY METRICS (FY2025 LATEST AVAILABLE)
B20: Company | C20: Mkt Cap (₹Cr) | D20: Revenue | E20: EBITDA Mgn | F20: Net Margin | G20: ROE | H20: P/E Ratio | I20: EV/EBITDA | J20: Div Yield | L20: Comment
B21: HUL | C21: 560000 | D21: 61469 | E21: 0.321 | F21: 0.235 | G21: 0.217 | H21: 52.5 | I21: 38.2 | J21: 0.018 | L21: Market leader; brand moat + consistent dividend support premium valuation.
B22: ITC Ltd | C22: 590000 | D22: 78540 | E22: 0.368 | F22: 0.281 | G22: 0.295 | H22: 26.7 | I22: 19.4 | J22: 0.029 | L22: Diversified; cigarette cash flows cross-subsidise FMCG. Lower P/E on ESG concerns.
B23: Nestlé India | C23: 240000 | D23: 26024 | E23: 0.256 | F23: 0.175 | G23: 0.82 | H23: 80.5 | I23: 54.8 | J23: 0.012 | L23: Monopoly brands (Maggi/KitKat); high ROE due to lean equity base.
B24: Dabur India | C24: 90000 | D24: 12562 | E24: 0.214 | F24: 0.132 | G24: 0.224 | H24: 54.3 | I24: 37.6 | J24: 0.015 | L24: Rural-focused herbal play; decelerating growth—modest premium.
B25: Britannia | C25: 120000 | D25: 17260 | E25: 0.189 | F25: 0.139 | G25: 0.576 | H25: 50.1 | I25: 33.5 | J25: 0.017 | L25: Capital-light bakery leader; high ROE; quality P/E premium.
A27: SECTION D — HUL IMPLIED FAIR VALUE (RELATIVE VALUATION SUMMARY)
B28: Method | C28: Peer Avg Multiple | D28: HUL Actual | E28: Basis / HUL Input | F28: Implied Price (₹) | G28: CMP (₹) | H28: Upside/Downside
B29: P/E Method | C29: 52.9 | D29: 52.5x | E29: Peer median P/E × EPS ₹44.55 | F29: 2357 | G29: 2350 | H29: 0.0029787234
B30: EV/EBITDA | C30: 36.3 | D30: 38.2x | E30: Peer EV/EBITDA × EBITDA/share | F30: 2285 | G30: 2350 | H30: -0.027659574
B31: P/Sales | C31: 4.1 | D31: 4.7x | E31: Peer P/Sales × Revenue/share | F31: 2275 | G31: 2350 | H31: -0.031914894
B32: P/Book Value | C32: 11.2 | D32: 11.0x | E32: Peer P/BV × BVPS ₹491.53 | F32: 5505 | G32: 2350 | H32: 1.3425532
B33: ▶ AVERAGE IMPLIED FAIR VALUE | F33: 3105 | G33: 2350 | H33: 0.3212766
A35: Note: CMP ₹2,350 used as reference. Peer averages exclude Nestlé outlier on P/E. All valuations are indicative; not investment advice.

Sheet Peer Master Data
A1: HINDUSTAN UNILEVER LIMITED — PEER MASTER DATA SHEET (FY2021–FY2025)
A2: All monetary values in ₹ Crores | Ratios as reported | Source: Annual Reports & Public Disclosures
B3: Company | C3: Year | D3: Revenue | E3: Net Income | F3: Total Assets | G3: Equity | H3: EBITDA Margin | I3: ROA | J3: ROE | K3: Current Ratio | L3: Debt-Equity | M3: Int. Coverage | N3: Asset Turnover | O3: Net Profit Mgn | P3: Eq. Multiplier
B4: HUL | C4: 2021 | D4: 45996 | E4: 10323 | F4: 54706 | G4: 47434 | H4: 0.304 | I4: 0.189 | J4: 0.218 | K4: 1.04 | L4: 0.02 | M4: 107.5 | N4: 0.841 | O4: 0.225 | P4: 1.15
B5: HUL | C5: 2022 | D5: 51193 | E5: 12386 | F5: 57620 | G5: 48760 | H5: 0.321 | I5: 0.215 | J5: 0.254 | K5: 1.04 | L5: 0.02 | M5: 131.2 | N5: 0.889 | O5: 0.242 | P5: 1.18
B6: HUL | C6: 2023 | D6: 59144 | E6: 13886 | F6: 60425 | G6: 50221 | H6: 0.307 | I6: 0.23 | J6: 0.277 | K6: 1.17 | L6: 0.021 | M6: 140.7 | N6: 0.979 | O6: 0.235 | P6: 1.2
B7: HUL | C7: 2024 | D7: 60469 | E7: 13775 | F7: 65410 | G7: 50973 | H7: 0.31 | I7: 0.211 | J7: 0.27 | K7: 1.31 | L7: 0.027 | M7: 49.9 | N7: 0.925 | O7: 0.228 | P7: 1.28
B8: HUL | C8: 2025 | D8: 61469 | E8: 14452 | F8: 60890 | G8: 49153 | H8: 0.32 | I8: 0.237 | J8: 0.294 | K8: 1.13 | L8: 0.031 | M8: 43.6 | N8: 1.009 | O8: 0.235 | P8: 1.24
B10: ITC Ltd | C10: 2021 | D10: 49258 | E10: 13383 | F10: 71500 | G10: 55420 | H10: 0.372 | I10: 0.187 | J10: 0.242 | K10: 2.15 | L10: 0.001 | M10: 420 | N10: 0.689 | O10: 0.272 | P10: 1.29
B11: ITC Ltd | C11: 2022 | D11: 59926 | E11: 16520 | F11: 78300 | G11: 59800 | H11: 0.375 | I11: 0.211 | J11: 0.276 | K11: 2.22 | L11: 0.001 | M11: 510 | N11: 0.765 | O11: 0.276 | P11: 1.31
B12: ITC Ltd | C12: 2023 | D12: 69481 | E12: 19194 | F12: 88400 | G12: 66200 | H12: 0.381 | I12: 0.217 | J12: 0.29 | K12: 2.1 | L12: 0.001 | M12: 580 | N12: 0.786 | O12: 0.276 | P12: 1.34
B13: ITC Ltd | C13: 2024 | D13: 71987 | E13: 20507 | F13: 96200 | G13: 72100 | H13: 0.368 | I13: 0.213 | J13: 0.284 | K13: 2.05 | L13: 0.001 | M13: 540 | N13: 0.748 | O13: 0.285 | P13: 1.33
B14: ITC Ltd | C14: 2025 | D14: 78540 | E14: 22075 | F14: 105000 | G14: 78300 | H14: 0.368 | I14: 0.21 | J14: 0.282 | K14: 2.18 | L14: 0.001 | M14: 590 | N14: 0.748 | O14: 0.281 | P14: 1.34
B16: Nestlé India | C16: 2021 | D16: 14076 | E16: 1911 | F16: 5420 | G16: 2340 | H16: 0.268 | I16: 0.353 | J16: 0.817 | K16: 1.05 | L16: 0 | M16: 180 | N16: 2.598 | O16: 0.136 | P16: 2.32
B17: Nestlé India | C17: 2022 | D17: 15943 | E17: 2461 | F17: 5900 | G17: 2610 | H17: 0.256 | I17: 0.417 | J17: 0.943 | K17: 1.12 | L17: 0 | M17: 220 | N17: 2.702 | O17: 0.154 | P17: 2.26
... B32: Britannia Ind | C32: 2025 | D32: 17260 | E32: 2402 | F32: 7400 | G32: 3380 | H32: 0.189 | I32: 0.325 | J32: 0.711 | K32: 1.02 | L32: 0.038 | M32: 120 | N32: 2.333 | O32: 0.139 | P32: 2.19
A33: Source: Annual Reports, BSE/NSE Filings, SEBI Disclosures. Consolidated financials used where available. Data reflects management reported figures.
